[
  {
    "coordinatesV1": "org.mnode.ical4j:ical4j:2.0-beta1",
    "coordinatesV2": "org.mnode.ical4j:ical4j:2.0-alpha1",
    "caller": "|java+constructor:///net/fortuna/ical4j/model/Recur/Recur(java.lang.String,int)|",
    "called": "|java+method:///org/apache/commons/logging/LogFactory/getLog(java.lang.Class)|",
    "v1Body": [
      "|java+method:///net/fortuna/ical4j/model/Recur/validateFrequency()|",
      "|java+constructor:///java/util/HashMap/HashMap()|",
      "|java+constructor:///java/lang/Object/Object()|",
      "|java+method:///org/apache/commons/logging/LogFactory/getLog(java.lang.Class)|"
    ],
    "v2Body": [
      "|java+method:///net/fortuna/ical4j/model/Recur/validateFrequency()|",
      "|java+method:///org/slf4j/LoggerFactory/getLogger(java.lang.Class)|",
      "|java+constructor:///java/util/HashMap/HashMap()|",
      "|java+constructor:///java/lang/Object/Object()|"
    ],
    "affectedLib": "org.slf4j:jcl-over-slf4j:1.7.7",
    "change": "REMOVED"
  },
  {
    "coordinatesV1": "org.mnode.ical4j:ical4j:2.0-beta1",
    "coordinatesV2": "org.mnode.ical4j:ical4j:2.0-alpha1",
    "caller": "|java+method:///net/fortuna/ical4j/filter/Filter/filter(java.lang.Object%5B%5D)|",
    "called": "|java+method:///org/apache/commons/logging/LogFactory/getLog(java.lang.Class)|",
    "v1Body": [
      "|java+method:///net/fortuna/ical4j/filter/Filter/filter(java.util.Collection)|",
      "|java+method:///java/lang/reflect/Array/newInstance(java.lang.Class,int)|",
      "|java+method:///java/util/Arrays/asList(java.lang.Object%5B%5D)|",
      "|java+method:///java/util/Collection/size()|",
      "|java+method:///java/util/Collection/toArray(java.lang.Object%5B%5D)|",
      "|java+method:///java/lang/Object/getClass()|",
      "|java+method:///org/apache/commons/logging/LogFactory/getLog(java.lang.Class)|",
      "|java+method:///org/apache/commons/logging/Log/warn(java.lang.Object,java.lang.Throwable)|",
      "|java+method:///java/util/Collection/toArray()|"
    ],
    "v2Body": [
      "|java+method:///org/slf4j/Logger/warn(java.lang.String,java.lang.Throwable)|",
      "|java+method:///net/fortuna/ical4j/filter/Filter/filter(java.util.Collection)|",
      "|java+method:///java/util/Collection/toArray()|",
      "|java+method:///java/lang/reflect/Array/newInstance(java.lang.Class,int)|",
      "|java+method:///java/util/Collection/size()|",
      "|java+method:///java/util/Collection/toArray(java.lang.Object%5B%5D)|",
      "|java+method:///java/lang/Object/getClass()|",
      "|java+method:///java/util/Arrays/asList(java.lang.Object%5B%5D)|",
      "|java+method:///org/slf4j/LoggerFactory/getLogger(java.lang.Class)|"
    ],
    "affectedLib": "org.slf4j:jcl-over-slf4j:1.7.7",
    "change": "REMOVED"
  },
  {
    "coordinatesV1": "org.mnode.ical4j:ical4j:2.0-beta1",
    "coordinatesV2": "org.mnode.ical4j:ical4j:2.0-alpha1",
    "caller": "|java+constructor:///net/fortuna/ical4j/model/Recur/Recur()|",
    "called": "|java+method:///org/apache/commons/logging/LogFactory/getLog(java.lang.Class)|",
    "v1Body": [
      "|java+constructor:///java/util/HashMap/HashMap()|",
      "|java+constructor:///java/lang/Object/Object()|",
      "|java+method:///org/apache/commons/logging/LogFactory/getLog(java.lang.Class)|"
    ],
    "v2Body": [
      "|java+method:///org/slf4j/LoggerFactory/getLogger(java.lang.Class)|",
      "|java+constructor:///java/util/HashMap/HashMap()|",
      "|java+constructor:///java/lang/Object/Object()|"
    ],
    "affectedLib": "org.slf4j:jcl-over-slf4j:1.7.7",
    "change": "REMOVED"
  },
  {
    "coordinatesV1": "org.mnode.ical4j:ical4j:2.0-beta1",
    "coordinatesV2": "org.mnode.ical4j:ical4j:2.0-alpha1",
    "caller": "|java+constructor:///net/fortuna/ical4j/model/Recur/Recur(java.lang.String)|",
    "called": "|java+method:///org/apache/commons/logging/LogFactory/getLog(java.lang.Class)|",
    "v1Body": [
      "|java+method:///java/util/Map/put(java.lang.Object,java.lang.Object)|",
      "|java+constructor:///net/fortuna/ical4j/model/WeekDayList/WeekDayList(java.lang.String)|",
      "|java+method:///net/fortuna/ical4j/model/DateTime/setUtc(boolean)|",
      "|java+constructor:///net/fortuna/ical4j/model/WeekDay/WeekDay(java.lang.String)|",
      "|java+method:///java/lang/String/format(java.lang.String,java.lang.Object%5B%5D)|",
      "|java+constructor:///java/util/HashMap/HashMap()|",
      "|java+method:///java/lang/String/equals(java.lang.Object)|",
      "|java+constructor:///net/fortuna/ical4j/model/NumberList/NumberList(java.lang.String,int,int,boolean)|",
      "|java+method:///java/lang/Integer/parseInt(java.lang.String)|",
      "|java+method:///java/lang/String/contains(java.lang.CharSequence)|",
      "|java+method:///java/util/StringTokenizer/hasMoreTokens()|",
      "|java+method:///net/fortuna/ical4j/model/Recur/nextToken(java.util.StringTokenizer,java.lang.String)|",
      "|java+method:///net/fortuna/ical4j/model/Recur/validateFrequency()|",
      "|java+constructor:///java/util/StringTokenizer/StringTokenizer(java.lang.String,java.lang.String)|",
      "|java+method:///net/fortuna/ical4j/model/WeekDay/getCalendarDay(net.fortuna.ical4j.model.WeekDay)|",
      "|java+method:///net/fortuna/ical4j/util/CompatibilityHints/isHintEnabled(java.lang.String)|",
      "|java+constructor:///net/fortuna/ical4j/model/Date/Date(java.lang.String)|",
      "|java+constructor:///net/fortuna/ical4j/model/DateTime/DateTime(java.lang.String)|",
      "|java+constructor:///java/lang/IllegalArgumentException/IllegalArgumentException(java.lang.String)|",
      "|java+method:///java/util/StringTokenizer/nextToken()|",
      "|java+constructor:///java/lang/Object/Object()|",
      "|java+method:///org/apache/commons/logging/LogFactory/getLog(java.lang.Class)|"
    ],
    "v2Body": [
      "|java+method:///java/util/Map/put(java.lang.Object,java.lang.Object)|",
      "|java+constructor:///net/fortuna/ical4j/model/WeekDayList/WeekDayList(java.lang.String)|",
      "|java+method:///net/fortuna/ical4j/model/DateTime/setUtc(boolean)|",
      "|java+constructor:///net/fortuna/ical4j/model/WeekDay/WeekDay(java.lang.String)|",
      "|java+method:///org/slf4j/LoggerFactory/getLogger(java.lang.Class)|",
      "|java+method:///java/lang/String/format(java.lang.String,java.lang.Object%5B%5D)|",
      "|java+constructor:///java/util/HashMap/HashMap()|",
      "|java+method:///java/lang/String/equals(java.lang.Object)|",
      "|java+constructor:///net/fortuna/ical4j/model/NumberList/NumberList(java.lang.String,int,int,boolean)|",
      "|java+method:///java/lang/Integer/parseInt(java.lang.String)|",
      "|java+method:///java/lang/String/contains(java.lang.CharSequence)|",
      "|java+method:///java/util/StringTokenizer/hasMoreTokens()|",
      "|java+method:///net/fortuna/ical4j/model/Recur/nextToken(java.util.StringTokenizer,java.lang.String)|",
      "|java+constructor:///java/lang/Object/Object()|",
      "|java+method:///net/fortuna/ical4j/model/Recur/validateFrequency()|",
      "|java+constructor:///java/util/StringTokenizer/StringTokenizer(java.lang.String,java.lang.String)|",
      "|java+method:///net/fortuna/ical4j/model/WeekDay/getCalendarDay(net.fortuna.ical4j.model.WeekDay)|",
      "|java+method:///net/fortuna/ical4j/util/CompatibilityHints/isHintEnabled(java.lang.String)|",
      "|java+constructor:///net/fortuna/ical4j/model/Date/Date(java.lang.String)|",
      "|java+constructor:///net/fortuna/ical4j/model/DateTime/DateTime(java.lang.String)|",
      "|java+constructor:///java/lang/IllegalArgumentException/IllegalArgumentException(java.lang.String)|",
      "|java+method:///java/util/StringTokenizer/nextToken()|"
    ],
    "affectedLib": "org.slf4j:jcl-over-slf4j:1.7.7",
    "change": "REMOVED"
  },
  {
    "coordinatesV1": "org.mnode.ical4j:ical4j:2.0-beta1",
    "coordinatesV2": "org.mnode.ical4j:ical4j:2.0-alpha1",
    "caller": "|java+constructor:///net/fortuna/ical4j/model/Recur/Recur(java.lang.String,net.fortuna.ical4j.model.Date)|",
    "called": "|java+method:///org/apache/commons/logging/LogFactory/getLog(java.lang.Class)|",
    "v1Body": [
      "|java+method:///net/fortuna/ical4j/model/Recur/validateFrequency()|",
      "|java+constructor:///java/util/HashMap/HashMap()|",
      "|java+constructor:///java/lang/Object/Object()|",
      "|java+method:///org/apache/commons/logging/LogFactory/getLog(java.lang.Class)|"
    ],
    "v2Body": [
      "|java+method:///net/fortuna/ical4j/model/Recur/validateFrequency()|",
      "|java+method:///org/slf4j/LoggerFactory/getLogger(java.lang.Class)|",
      "|java+constructor:///java/util/HashMap/HashMap()|",
      "|java+constructor:///java/lang/Object/Object()|"
    ],
    "affectedLib": "org.slf4j:jcl-over-slf4j:1.7.7",
    "change": "REMOVED"
  },
  {
    "coordinatesV1": "org.mnode.ical4j:ical4j:2.0-beta1",
    "coordinatesV2": "org.mnode.ical4j:ical4j:2.0-alpha1",
    "caller": "|java+initializer:///net/fortuna/ical4j/data/HCalendarParser/HCalendarParser$initializer|",
    "called": "|java+method:///org/apache/commons/logging/LogFactory/getLog(java.lang.Class)|",
    "v1Body": [
      "|java+method:///net/fortuna/ical4j/data/HCalendarParser/compileExpression(java.lang.String)|",
      "|java+method:///javax/xml/xpath/XPathFactory/newInstance()|",
      "|java+method:///javax/xml/parsers/DocumentBuilderFactory/newInstance()|",
      "|java+method:///org/apache/commons/logging/LogFactory/getLog(java.lang.Class)|",
      "|java+constructor:///java/text/SimpleDateFormat/SimpleDateFormat(java.lang.String)|",
      "|java+method:///javax/xml/parsers/DocumentBuilderFactory/setNamespaceAware(boolean)|",
      "|java+method:///javax/xml/xpath/XPathFactory/newXPath()|",
      "|java+method:///javax/xml/parsers/DocumentBuilderFactory/setIgnoringComments(boolean)|"
    ],
    "v2Body": [
      "|java+method:///net/fortuna/ical4j/data/HCalendarParser/compileExpression(java.lang.String)|",
      "|java+method:///org/slf4j/LoggerFactory/getLogger(java.lang.Class)|",
      "|java+method:///javax/xml/xpath/XPathFactory/newInstance()|",
      "|java+method:///javax/xml/parsers/DocumentBuilderFactory/newInstance()|",
      "|java+constructor:///java/text/SimpleDateFormat/SimpleDateFormat(java.lang.String)|",
      "|java+method:///javax/xml/parsers/DocumentBuilderFactory/setNamespaceAware(boolean)|",
      "|java+method:///javax/xml/xpath/XPathFactory/newXPath()|",
      "|java+method:///javax/xml/parsers/DocumentBuilderFactory/setIgnoringComments(boolean)|"
    ],
    "affectedLib": "org.slf4j:jcl-over-slf4j:1.7.7",
    "change": "REMOVED"
  },
  {
    "coordinatesV1": "org.mnode.ical4j:ical4j:2.0-beta1",
    "coordinatesV2": "org.mnode.ical4j:ical4j:2.0-alpha1",
    "caller": "|java+method:///net/fortuna/ical4j/data/CalendarBuilder/updateTimeZone(net.fortuna.ical4j.model.Property,net.fortuna.ical4j.model.TimeZone)|",
    "called": "|java+method:///org/apache/commons/logging/LogFactory/getLog(java.lang.Class)|",
    "v1Body": [
      "|java+method:///org/apache/commons/logging/Log/warn(java.lang.Object,java.lang.Throwable)|",
      "|java+method:///java/lang/StringBuilder/append(java.lang.String)|",
      "|java+method:///net/fortuna/ical4j/model/property/DateProperty/setTimeZone(net.fortuna.ical4j.model.TimeZone)|",
      "|java+method:///net/fortuna/ical4j/model/property/DateListProperty/setTimeZone(net.fortuna.ical4j.model.TimeZone)|",
      "|java+method:///net/fortuna/ical4j/model/TimeZone/getID()|",
      "|java+method:///net/fortuna/ical4j/util/CompatibilityHints/isHintEnabled(java.lang.String)|",
      "|java+constructor:///java/lang/StringBuilder/StringBuilder()|",
      "|java+method:///net/fortuna/ical4j/model/Property/getName()|",
      "|java+method:///org/apache/commons/logging/LogFactory/getLog(java.lang.Class)|",
      "|java+method:///java/lang/StringBuilder/toString()|"
    ],
    "v2Body": [
      "|java+method:///org/slf4j/Logger/warn(java.lang.String,java.lang.Throwable)|",
      "|java+method:///java/lang/StringBuilder/append(java.lang.String)|",
      "|java+method:///net/fortuna/ical4j/model/property/DateProperty/setTimeZone(net.fortuna.ical4j.model.TimeZone)|",
      "|java+method:///net/fortuna/ical4j/model/TimeZone/getID()|",
      "|java+method:///net/fortuna/ical4j/util/CompatibilityHints/isHintEnabled(java.lang.String)|",
      "|java+constructor:///java/lang/StringBuilder/StringBuilder()|",
      "|java+method:///net/fortuna/ical4j/model/Property/getName()|",
      "|java+method:///java/lang/StringBuilder/toString()|",
      "|java+method:///net/fortuna/ical4j/model/property/DateListProperty/setTimeZone(net.fortuna.ical4j.model.TimeZone)|",
      "|java+method:///org/slf4j/LoggerFactory/getLogger(java.lang.Class)|"
    ],
    "affectedLib": "org.slf4j:jcl-over-slf4j:1.7.7",
    "change": "REMOVED"
  },
  {
    "coordinatesV1": "org.mnode.ical4j:ical4j:2.0-beta1",
    "coordinatesV2": "org.mnode.ical4j:ical4j:2.0-alpha1",
    "caller": "|java+method:///net/fortuna/ical4j/model/property/Attach/getValue()|",
    "called": "|java+method:///org/apache/commons/logging/LogFactory/getLog(java.lang.Class)|",
    "v1Body": [
      "|java+method:///net/fortuna/ical4j/util/EncoderFactory/getInstance()|",
      "|java+method:///net/fortuna/ical4j/util/EncoderFactory/createBinaryEncoder(net.fortuna.ical4j.model.parameter.Encoding)|",
      "|java+method:///net/fortuna/ical4j/util/Strings/valueOf(java.lang.Object)|",
      "|java+method:///net/fortuna/ical4j/model/property/Attach/getBinary()|",
      "|java+method:///org/apache/commons/codec/BinaryEncoder/encode(byte%5B%5D)|",
      "|java+constructor:///java/lang/String/String(byte%5B%5D)|",
      "|java+method:///org/apache/commons/logging/Log/error(java.lang.Object,java.lang.Throwable)|",
      "|java+method:///net/fortuna/ical4j/model/property/Attach/getUri()|",
      "|java+method:///org/apache/commons/logging/LogFactory/getLog(java.lang.Class)|",
      "|java+method:///net/fortuna/ical4j/model/property/Attach/getParameter(java.lang.String)|",
      "|java+method:///net/fortuna/ical4j/util/Uris/decode(java.lang.String)|"
    ],
    "v2Body": [
      "|java+method:///net/fortuna/ical4j/util/EncoderFactory/getInstance()|",
      "|java+method:///net/fortuna/ical4j/util/EncoderFactory/createBinaryEncoder(net.fortuna.ical4j.model.parameter.Encoding)|",
      "|java+method:///net/fortuna/ical4j/util/Strings/valueOf(java.lang.Object)|",
      "|java+method:///net/fortuna/ical4j/model/property/Attach/getBinary()|",
      "|java+method:///org/slf4j/LoggerFactory/getLogger(java.lang.Class)|",
      "|java+method:///org/apache/commons/codec/BinaryEncoder/encode(byte%5B%5D)|",
      "|java+constructor:///java/lang/String/String(byte%5B%5D)|",
      "|java+method:///org/slf4j/Logger/error(java.lang.String,java.lang.Throwable)|",
      "|java+method:///net/fortuna/ical4j/model/property/Attach/getUri()|",
      "|java+method:///net/fortuna/ical4j/model/property/Attach/getParameter(java.lang.String)|",
      "|java+method:///net/fortuna/ical4j/util/Uris/decode(java.lang.String)|"
    ],
    "affectedLib": "org.slf4j:jcl-over-slf4j:1.7.7",
    "change": "REMOVED"
  },
  {
    "coordinatesV1": "org.mnode.ical4j:ical4j:2.0-beta1",
    "coordinatesV2": "org.mnode.ical4j:ical4j:2.0-alpha1",
    "caller": "|java+constructor:///net/fortuna/ical4j/data/UnfoldingReader/UnfoldingReader(java.io.Reader,int,boolean)|",
    "called": "|java+method:///org/apache/commons/logging/LogFactory/getLog(java.lang.Class)|",
    "v1Body": [
      "|java+method:///java/lang/Math/max(int,int)|",
      "|java+constructor:///java/io/PushbackReader/PushbackReader(java.io.Reader,int)|",
      "|java+method:///org/apache/commons/logging/LogFactory/getLog(java.lang.Class)|"
    ],
    "v2Body": [
      "|java+method:///java/lang/Math/max(int,int)|",
      "|java+method:///org/slf4j/LoggerFactory/getLogger(java.lang.Class)|",
      "|java+constructor:///java/io/PushbackReader/PushbackReader(java.io.Reader,int)|"
    ],
    "affectedLib": "org.slf4j:jcl-over-slf4j:1.7.7",
    "change": "REMOVED"
  },
  {
    "coordinatesV1": "org.mnode.ical4j:ical4j:2.0-beta1",
    "coordinatesV2": "org.mnode.ical4j:ical4j:2.0-alpha1",
    "caller": "|java+method:///net/fortuna/ical4j/model/TimeZoneRegistryImpl/getTimeZone(java.lang.String)|",
    "called": "|java+method:///org/apache/commons/logging/LogFactory/getLog(java.lang.Class)|",
    "v1Body": [
      "|java+method:///java/util/Map/put(java.lang.Object,java.lang.Object)|",
      "|java+method:///net/fortuna/ical4j/model/TimeZoneRegistryImpl/getTimeZone(java.lang.String)|",
      "|java+method:///java/util/Properties/getProperty(java.lang.String)|",
      "|java+method:///org/apache/commons/logging/Log/warn(java.lang.Object,java.lang.Throwable)|",
      "|java+method:///java/util/Map/get(java.lang.Object)|",
      "|java+method:///net/fortuna/ical4j/model/TimeZone/getID()|",
      "|java+method:///net/fortuna/ical4j/util/CompatibilityHints/isHintEnabled(java.lang.String)|",
      "|java+constructor:///net/fortuna/ical4j/model/TimeZone/TimeZone(net.fortuna.ical4j.model.component.VTimeZone)|",
      "|java+method:///java/util/regex/Matcher/group()|",
      "|java+method:///java/util/regex/Matcher/find()|",
      "|java+method:///java/util/regex/Pattern/matcher(java.lang.CharSequence)|",
      "|java+method:///net/fortuna/ical4j/model/TimeZoneRegistryImpl/loadVTimeZone(java.lang.String)|",
      "|java+method:///org/apache/commons/logging/LogFactory/getLog(java.lang.Class)|"
    ],
    "v2Body": [
      "|java+method:///java/util/Map/put(java.lang.Object,java.lang.Object)|",
      "|java+method:///net/fortuna/ical4j/model/TimeZoneRegistryImpl/getTimeZone(java.lang.String)|",
      "|java+method:///java/util/Properties/getProperty(java.lang.String)|",
      "|java+method:///org/slf4j/Logger/warn(java.lang.String,java.lang.Throwable)|",
      "|java+method:///net/fortuna/ical4j/model/TimeZone/getID()|",
      "|java+method:///net/fortuna/ical4j/util/CompatibilityHints/isHintEnabled(java.lang.String)|",
      "|java+constructor:///net/fortuna/ical4j/model/TimeZone/TimeZone(net.fortuna.ical4j.model.component.VTimeZone)|",
      "|java+method:///java/util/regex/Matcher/group()|",
      "|java+method:///java/util/regex/Matcher/find()|",
      "|java+method:///java/util/regex/Pattern/matcher(java.lang.CharSequence)|",
      "|java+method:///net/fortuna/ical4j/model/TimeZoneRegistryImpl/loadVTimeZone(java.lang.String)|",
      "|java+method:///java/util/Map/get(java.lang.Object)|",
      "|java+method:///org/slf4j/LoggerFactory/getLogger(java.lang.Class)|"
    ],
    "affectedLib": "org.slf4j:jcl-over-slf4j:1.7.7",
    "change": "REMOVED"
  },
  {
    "coordinatesV1": "org.mnode.ical4j:ical4j:2.0-beta1",
    "coordinatesV2": "org.mnode.ical4j:ical4j:2.0-alpha1",
    "caller": "|java+initializer:///net/fortuna/ical4j/model/TimeZoneRegistryImpl/TimeZoneRegistryImpl$initializer|",
    "called": "|java+method:///org/apache/commons/logging/LogFactory/getLog(java.lang.Class)|",
    "v1Body": [
      "|java+method:///org/apache/commons/logging/Log/debug(java.lang.Object)|",
      "|java+method:///java/util/regex/Pattern/compile(java.lang.String)|",
      "|java+method:///org/apache/commons/logging/Log/warn(java.lang.Object)|",
      "|java+method:///java/io/IOException/getMessage()|",
      "|java+constructor:///java/util/Properties/Properties()|",
      "|java+constructor:///java/lang/StringBuilder/StringBuilder()|",
      "|java+method:///org/apache/commons/logging/LogFactory/getLog(java.lang.Class)|",
      "|java+method:///java/lang/StringBuilder/append(java.lang.String)|",
      "|java+constructor:///java/util/concurrent/ConcurrentHashMap/ConcurrentHashMap()|",
      "|java+method:///net/fortuna/ical4j/util/ResourceLoader/getResourceAsStream(java.lang.String)|",
      "|java+method:///java/util/Properties/load(java.io.InputStream)|",
      "|java+method:///java/lang/StringBuilder/toString()|",
      "|java+method:///java/lang/Exception/getMessage()|"
    ],
    "v2Body": [
      "|java+method:///org/slf4j/Logger/debug(java.lang.String)|",
      "|java+method:///java/io/IOException/getMessage()|",
      "|java+method:///java/lang/Throwable/getMessage()|",
      "|java+method:///java/io/InputStream/close()|",
      "|java+constructor:///java/lang/StringBuilder/StringBuilder()|",
      "|java+method:///java/lang/Integer/parseInt(java.lang.String)|",
      "|java+method:///net/fortuna/ical4j/util/Configurator/getProperty(java.lang.String)|",
      "|java+method:///java/util/regex/Pattern/compile(java.lang.String)|",
      "|java+constructor:///java/net/InetSocketAddress/InetSocketAddress(java.lang.String,int)|",
      "|java+method:///org/slf4j/Logger/warn(java.lang.String)|",
      "|java+method:///java/lang/StringBuilder/append(java.lang.String)|",
      "|java+constructor:///java/util/concurrent/ConcurrentHashMap/ConcurrentHashMap()|",
      "|java+constructor:///java/net/Proxy/Proxy(java.net.Proxy$Type,java.net.SocketAddress)|",
      "|java+method:///org/slf4j/LoggerFactory/getLogger(java.lang.Class)|",
      "|java+method:///java/lang/String/equals(java.lang.Object)|",
      "|java+constructor:///java/util/Properties/Properties()|",
      "|java+method:///net/fortuna/ical4j/util/ResourceLoader/getResourceAsStream(java.lang.String)|",
      "|java+method:///java/util/Properties/load(java.io.InputStream)|",
      "|java+method:///java/lang/StringBuilder/toString()|",
      "|java+method:///java/lang/Exception/getMessage()|",
      "|java+method:///java/net/Proxy$Type/valueOf(java.lang.String)|"
    ],
    "affectedLib": "org.slf4j:jcl-over-slf4j:1.7.7",
    "change": "REMOVED"
  },
  {
    "coordinatesV1": "org.mnode.ical4j:ical4j:2.0-beta1",
    "coordinatesV2": "org.mnode.ical4j:ical4j:2.0-alpha1",
    "caller": "|java+constructor:///net/fortuna/ical4j/data/FoldingWriter/FoldingWriter(java.io.Writer,int)|",
    "called": "|java+method:///org/apache/commons/logging/LogFactory/getLog(java.lang.Class)|",
    "v1Body": [
      "|java+constructor:///java/io/FilterWriter/FilterWriter(java.io.Writer)|",
      "|java+method:///java/lang/Math/min(int,int)|",
      "|java+method:///org/apache/commons/logging/LogFactory/getLog(java.lang.Class)|"
    ],
    "v2Body": [
      "|java+constructor:///java/io/FilterWriter/FilterWriter(java.io.Writer)|",
      "|java+method:///org/slf4j/LoggerFactory/getLogger(java.lang.Class)|",
      "|java+method:///java/lang/Math/min(int,int)|"
    ],
    "affectedLib": "org.slf4j:jcl-over-slf4j:1.7.7",
    "change": "REMOVED"
  },
  {
    "coordinatesV1": "org.mnode.ical4j:ical4j:2.0-beta1",
    "coordinatesV2": "org.mnode.ical4j:ical4j:2.0-alpha1",
    "caller": "|java+method:///net/fortuna/ical4j/model/component/Observance/getLatestOnset(net.fortuna.ical4j.model.Date)|",
    "called": "|java+method:///org/apache/commons/logging/LogFactory/getLog(java.lang.Class)|",
    "v1Body": [
      "|java+method:///net/fortuna/ical4j/model/DateTime/getTime()|",
      "|java+method:///net/fortuna/ical4j/util/Dates/getCalendarInstance(net.fortuna.ical4j.model.Date)|",
      "|java+method:///java/util/Iterator/hasNext()|",
      "|java+method:///net/fortuna/ical4j/model/DateList/size()|",
      "|java+method:///java/util/Iterator/next()|",
      "|java+method:///net/fortuna/ical4j/model/component/Observance/getProperties(java.lang.String)|",
      "|java+method:///net/fortuna/ical4j/model/component/Observance/getProperty(java.lang.String)|",
      "|java+method:///java/util/Collections/sort(java.util.List)|",
      "|java+method:///org/apache/commons/logging/Log/error(java.lang.Object,java.lang.Throwable)|",
      "|java+constructor:///net/fortuna/ical4j/model/DateList/DateList()|",
      "|java+method:///org/apache/commons/logging/LogFactory/getLog(java.lang.Class)|",
      "|java+method:///net/fortuna/ical4j/model/property/DtStart/getDate()|",
      "|java+method:///java/util/Calendar/setTime(java.util.Date)|",
      "|java+method:///java/util/Calendar/add(int,int)|",
      "|java+method:///java/util/Calendar/getTime()|",
      "|java+method:///net/fortuna/ical4j/model/DateTime/after(java.util.Date)|",
      "|java+method:///net/fortuna/ical4j/model/component/Observance/getCachedOnset(net.fortuna.ical4j.model.Date)|",
      "|java+method:///net/fortuna/ical4j/model/PropertyList/iterator()|",
      "|java+method:///net/fortuna/ical4j/model/DateList/add(net.fortuna.ical4j.model.Date)|",
      "|java+method:///net/fortuna/ical4j/model/DateList/get(int)|",
      "|java+method:///net/fortuna/ical4j/util/Dates/getInstance(java.util.Date,net.fortuna.ical4j.model.parameter.Value)|",
      "|java+method:///net/fortuna/ical4j/model/DateList/setUtc(boolean)|",
      "|java+method:///net/fortuna/ical4j/model/DateList/iterator()|",
      "|java+method:///net/fortuna/ical4j/model/Date/before(java.util.Date)|",
      "|java+method:///net/fortuna/ical4j/model/property/RRule/getRecur()|",
      "|java+method:///net/fortuna/ical4j/model/component/Observance/calculateOnset(net.fortuna.ical4j.model.Date)|",
      "|java+method:///net/fortuna/ical4j/model/property/RDate/getDates()|",
      "|java+method:///net/fortuna/ical4j/model/Recur/getDates(net.fortuna.ical4j.model.Date,net.fortuna.ical4j.model.Date,net.fortuna.ical4j.model.parameter.Value)|",
      "|java+method:///net/fortuna/ical4j/model/component/Observance/applyOffsetFrom(net.fortuna.ical4j.model.DateTime)|"
    ],
    "v2Body": [
      "|java+method:///net/fortuna/ical4j/model/DateTime/getTime()|",
      "|java+method:///net/fortuna/ical4j/util/Dates/getCalendarInstance(net.fortuna.ical4j.model.Date)|",
      "|java+method:///java/util/Iterator/hasNext()|",
      "|java+method:///net/fortuna/ical4j/model/DateList/size()|",
      "|java+method:///java/util/Iterator/next()|",
      "|java+method:///net/fortuna/ical4j/model/component/Observance/getProperties(java.lang.String)|",
      "|java+method:///net/fortuna/ical4j/model/component/Observance/getProperty(java.lang.String)|",
      "|java+method:///java/util/Collections/sort(java.util.List)|",
      "|java+constructor:///net/fortuna/ical4j/model/DateList/DateList()|",
      "|java+method:///net/fortuna/ical4j/model/property/DtStart/getDate()|",
      "|java+method:///java/util/Calendar/setTime(java.util.Date)|",
      "|java+method:///java/util/Calendar/add(int,int)|",
      "|java+method:///java/util/Calendar/getTime()|",
      "|java+method:///org/slf4j/LoggerFactory/getLogger(java.lang.Class)|",
      "|java+method:///net/fortuna/ical4j/model/DateTime/after(java.util.Date)|",
      "|java+method:///net/fortuna/ical4j/model/component/Observance/getCachedOnset(net.fortuna.ical4j.model.Date)|",
      "|java+method:///net/fortuna/ical4j/model/PropertyList/iterator()|",
      "|java+method:///net/fortuna/ical4j/model/DateList/add(net.fortuna.ical4j.model.Date)|",
      "|java+method:///net/fortuna/ical4j/model/DateList/get(int)|",
      "|java+method:///net/fortuna/ical4j/util/Dates/getInstance(java.util.Date,net.fortuna.ical4j.model.parameter.Value)|",
      "|java+method:///org/slf4j/Logger/error(java.lang.String,java.lang.Throwable)|",
      "|java+method:///net/fortuna/ical4j/model/DateList/setUtc(boolean)|",
      "|java+method:///net/fortuna/ical4j/model/DateList/iterator()|",
      "|java+method:///net/fortuna/ical4j/model/Date/before(java.util.Date)|",
      "|java+method:///net/fortuna/ical4j/model/property/RRule/getRecur()|",
      "|java+method:///net/fortuna/ical4j/model/component/Observance/calculateOnset(net.fortuna.ical4j.model.Date)|",
      "|java+method:///net/fortuna/ical4j/model/property/RDate/getDates()|",
      "|java+method:///net/fortuna/ical4j/model/Recur/getDates(net.fortuna.ical4j.model.Date,net.fortuna.ical4j.model.Date,net.fortuna.ical4j.model.parameter.Value)|",
      "|java+method:///net/fortuna/ical4j/model/component/Observance/applyOffsetFrom(net.fortuna.ical4j.model.DateTime)|"
    ],
    "affectedLib": "org.slf4j:jcl-over-slf4j:1.7.7",
    "change": "REMOVED"
  },
  {
    "coordinatesV1": "org.mnode.ical4j:ical4j:2.0-beta1",
    "coordinatesV2": "org.mnode.ical4j:ical4j:2.0-alpha1",
    "caller": "|java+initializer:///net/fortuna/ical4j/util/ResourceLoader/ResourceLoader$initializer|",
    "called": "|java+method:///org/apache/commons/logging/LogFactory/getLog(java.lang.Class)|",
    "v1Body": [
      "|java+method:///org/apache/commons/logging/LogFactory/getLog(java.lang.Class)|"
    ],
    "v2Body": [
      "|java+method:///org/slf4j/LoggerFactory/getLogger(java.lang.Class)|"
    ],
    "affectedLib": "org.slf4j:jcl-over-slf4j:1.7.7",
    "change": "REMOVED"
  },
  {
    "coordinatesV1": "org.mnode.ical4j:ical4j:2.0-beta1",
    "coordinatesV2": "org.mnode.ical4j:ical4j:2.0-alpha1",
    "caller": "|java+method:///net/fortuna/ical4j/model/Recur/readObject(java.io.ObjectInputStream)|",
    "called": "|java+method:///org/apache/commons/logging/LogFactory/getLog(java.lang.Class)|",
    "v1Body": [
      "|java+method:///java/io/ObjectInputStream/defaultReadObject()|",
      "|java+method:///org/apache/commons/logging/LogFactory/getLog(java.lang.Class)|"
    ],
    "v2Body": [
      "|java+method:///org/slf4j/LoggerFactory/getLogger(java.lang.Class)|",
      "|java+method:///java/io/ObjectInputStream/defaultReadObject()|"
    ],
    "affectedLib": "org.slf4j:jcl-over-slf4j:1.7.7",
    "change": "REMOVED"
  },
  {
    "coordinatesV1": "org.mnode.ical4j:ical4j:2.0-beta1",
    "coordinatesV2": "org.mnode.ical4j:ical4j:2.0-alpha1",
    "caller": "|java+constructor:///net/fortuna/ical4j/data/CalendarParserImpl/CalendarParserImpl()|",
    "called": "|java+method:///org/apache/commons/logging/LogFactory/getLog(java.lang.Class)|",
    "v1Body": [
      "|java+constructor:///net/fortuna/ical4j/data/CalendarParserImpl$PropertyParser/CalendarParserImpl$PropertyParser(net.fortuna.ical4j.data.CalendarParserImpl,net.fortuna.ical4j.data.CalendarParserImpl$1)|",
      "|java+constructor:///net/fortuna/ical4j/data/CalendarParserImpl$PropertyListParser/CalendarParserImpl$PropertyListParser(net.fortuna.ical4j.data.CalendarParserImpl,net.fortuna.ical4j.data.CalendarParserImpl$1)|",
      "|java+constructor:///net/fortuna/ical4j/data/CalendarParserImpl$ComponentParser/CalendarParserImpl$ComponentParser(net.fortuna.ical4j.data.CalendarParserImpl,net.fortuna.ical4j.data.CalendarParserImpl$1)|",
      "|java+constructor:///net/fortuna/ical4j/data/CalendarParserImpl$ParameterListParser/CalendarParserImpl$ParameterListParser(net.fortuna.ical4j.data.CalendarParserImpl,net.fortuna.ical4j.data.CalendarParserImpl$1)|",
      "|java+constructor:///java/lang/Object/Object()|",
      "|java+method:///org/apache/commons/logging/LogFactory/getLog(java.lang.Class)|",
      "|java+constructor:///net/fortuna/ical4j/data/CalendarParserImpl$ComponentListParser/CalendarParserImpl$ComponentListParser(net.fortuna.ical4j.data.CalendarParserImpl,net.fortuna.ical4j.data.CalendarParserImpl$1)|",
      "|java+constructor:///net/fortuna/ical4j/data/CalendarParserImpl$ParameterParser/CalendarParserImpl$ParameterParser(net.fortuna.ical4j.data.CalendarParserImpl,net.fortuna.ical4j.data.CalendarParserImpl$1)|"
    ],
    "v2Body": [
      "|java+constructor:///net/fortuna/ical4j/data/CalendarParserImpl$PropertyParser/CalendarParserImpl$PropertyParser(net.fortuna.ical4j.data.CalendarParserImpl,net.fortuna.ical4j.data.CalendarParserImpl$1)|",
      "|java+constructor:///net/fortuna/ical4j/data/CalendarParserImpl$PropertyListParser/CalendarParserImpl$PropertyListParser(net.fortuna.ical4j.data.CalendarParserImpl,net.fortuna.ical4j.data.CalendarParserImpl$1)|",
      "|java+method:///org/slf4j/LoggerFactory/getLogger(java.lang.Class)|",
      "|java+constructor:///net/fortuna/ical4j/data/CalendarParserImpl$ComponentParser/CalendarParserImpl$ComponentParser(net.fortuna.ical4j.data.CalendarParserImpl,net.fortuna.ical4j.data.CalendarParserImpl$1)|",
      "|java+constructor:///net/fortuna/ical4j/data/CalendarParserImpl$ParameterListParser/CalendarParserImpl$ParameterListParser(net.fortuna.ical4j.data.CalendarParserImpl,net.fortuna.ical4j.data.CalendarParserImpl$1)|",
      "|java+constructor:///java/lang/Object/Object()|",
      "|java+constructor:///net/fortuna/ical4j/data/CalendarParserImpl$ComponentListParser/CalendarParserImpl$ComponentListParser(net.fortuna.ical4j.data.CalendarParserImpl,net.fortuna.ical4j.data.CalendarParserImpl$1)|",
      "|java+constructor:///net/fortuna/ical4j/data/CalendarParserImpl$ParameterParser/CalendarParserImpl$ParameterParser(net.fortuna.ical4j.data.CalendarParserImpl,net.fortuna.ical4j.data.CalendarParserImpl$1)|"
    ],
    "affectedLib": "org.slf4j:jcl-over-slf4j:1.7.7",
    "change": "REMOVED"
  },
  {
    "coordinatesV1": "org.mnode.ical4j:ical4j:2.0-beta1",
    "coordinatesV2": "org.mnode.ical4j:ical4j:2.0-alpha1",
    "caller": "|java+initializer:///net/fortuna/ical4j/model/CalendarDateFormatFactory/CalendarDateFormatFactory$initializer|",
    "called": "|java+method:///org/apache/commons/logging/LogFactory/getLog(java.lang.Class)|",
    "v1Body": [
      "|java+method:///org/apache/commons/logging/LogFactory/getLog(java.lang.Class)|"
    ],
    "v2Body": [
      "|java+method:///org/slf4j/LoggerFactory/getLogger(java.lang.Class)|"
    ],
    "affectedLib": "org.slf4j:jcl-over-slf4j:1.7.7",
    "change": "REMOVED"
  },
  {
    "coordinatesV1": "org.mnode.ical4j:ical4j:2.0-beta1",
    "coordinatesV2": "org.mnode.ical4j:ical4j:2.0-alpha1",
    "caller": "|java+initializer:///net/fortuna/ical4j/util/Configurator/Configurator$initializer|",
    "called": "|java+method:///org/apache/commons/logging/LogFactory/getLog(java.lang.Class)|",
    "v1Body": [
      "|java+method:///org/apache/commons/logging/Log/info(java.lang.Object)|",
      "|java+constructor:///java/util/Properties/Properties()|",
      "|java+method:///org/apache/commons/logging/LogFactory/getLog(java.lang.Class)|",
      "|java+method:///net/fortuna/ical4j/util/ResourceLoader/getResourceAsStream(java.lang.String)|",
      "|java+method:///java/util/Properties/load(java.io.InputStream)|"
    ],
    "v2Body": [
      "|java+method:///org/slf4j/LoggerFactory/getLogger(java.lang.Class)|",
      "|java+method:///org/slf4j/Logger/info(java.lang.String)|",
      "|java+constructor:///java/util/Properties/Properties()|",
      "|java+method:///net/fortuna/ical4j/util/ResourceLoader/getResourceAsStream(java.lang.String)|",
      "|java+method:///java/util/Properties/load(java.io.InputStream)|"
    ],
    "affectedLib": "org.slf4j:jcl-over-slf4j:1.7.7",
    "change": "REMOVED"
  },
  {
    "coordinatesV1": "org.mnode.ical4j:ical4j:2.0-beta1",
    "coordinatesV2": "org.mnode.ical4j:ical4j:2.0-alpha1",
    "caller": "|java+method:///net/fortuna/ical4j/model/property/Attach/setValue(java.lang.String)|",
    "called": "|java+method:///org/apache/commons/logging/LogFactory/getLog(java.lang.Class)|",
    "v1Body": [
      "|java+method:///org/apache/commons/codec/BinaryDecoder/decode(byte%5B%5D)|",
      "|java+method:///net/fortuna/ical4j/util/DecoderFactory/createBinaryDecoder(net.fortuna.ical4j.model.parameter.Encoding)|",
      "|java+method:///net/fortuna/ical4j/model/property/Attach/getParameter(java.lang.String)|",
      "|java+method:///org/apache/commons/logging/Log/error(java.lang.Object,java.lang.Throwable)|",
      "|java+method:///net/fortuna/ical4j/util/DecoderFactory/getInstance()|",
      "|java+method:///java/lang/String/getBytes()|",
      "|java+method:///org/apache/commons/logging/LogFactory/getLog(java.lang.Class)|",
      "|java+method:///net/fortuna/ical4j/util/Uris/create(java.lang.String)|"
    ],
    "v2Body": [
      "|java+method:///org/apache/commons/codec/BinaryDecoder/decode(byte%5B%5D)|",
      "|java+method:///net/fortuna/ical4j/util/DecoderFactory/createBinaryDecoder(net.fortuna.ical4j.model.parameter.Encoding)|",
      "|java+method:///org/slf4j/LoggerFactory/getLogger(java.lang.Class)|",
      "|java+method:///net/fortuna/ical4j/model/property/Attach/getParameter(java.lang.String)|",
      "|java+method:///org/slf4j/Logger/error(java.lang.String,java.lang.Throwable)|",
      "|java+method:///net/fortuna/ical4j/util/DecoderFactory/getInstance()|",
      "|java+method:///java/lang/String/getBytes()|",
      "|java+method:///net/fortuna/ical4j/util/Uris/create(java.lang.String)|"
    ],
    "affectedLib": "org.slf4j:jcl-over-slf4j:1.7.7",
    "change": "REMOVED"
  },
  {
    "coordinatesV1": "org.mnode.ical4j:ical4j:2.0-beta1",
    "coordinatesV2": "org.mnode.ical4j:ical4j:2.0-alpha1",
    "caller": "|java+method:///net/fortuna/ical4j/model/TimeZoneRegistryImpl/updateDefinition(net.fortuna.ical4j.model.component.VTimeZone)|",
    "called": "|java+method:///org/apache/commons/logging/LogFactory/getLog(java.lang.Class)|",
    "v1Body": [
      "|java+method:///net/fortuna/ical4j/model/property/TzId/getValue()|",
      "|java+method:///net/fortuna/ical4j/model/component/VTimeZone/getTimeZoneUrl()|",
      "|java+method:///java/net/URL/openStream()|",
      "|java+method:///org/apache/commons/logging/Log/warn(java.lang.Object,java.lang.Throwable)|",
      "|java+method:///java/lang/StringBuilder/append(java.lang.String)|",
      "|java+method:///java/net/URI/toURL()|",
      "|java+constructor:///java/lang/StringBuilder/StringBuilder()|",
      "|java+method:///net/fortuna/ical4j/data/CalendarBuilder/build(java.io.InputStream)|",
      "|java+method:///net/fortuna/ical4j/model/Calendar/getComponent(java.lang.String)|",
      "|java+constructor:///net/fortuna/ical4j/data/CalendarBuilder/CalendarBuilder()|",
      "|java+method:///net/fortuna/ical4j/model/property/TzUrl/getUri()|",
      "|java+method:///net/fortuna/ical4j/model/component/VTimeZone/getTimeZoneId()|",
      "|java+method:///org/apache/commons/logging/LogFactory/getLog(java.lang.Class)|",
      "|java+method:///java/lang/StringBuilder/toString()|"
    ],
    "v2Body": [
      "|java+method:///net/fortuna/ical4j/model/property/TzId/getValue()|",
      "|java+method:///net/fortuna/ical4j/model/component/VTimeZone/getTimeZoneUrl()|",
      "|java+method:///java/lang/StringBuilder/append(java.lang.String)|",
      "|java+constructor:///java/lang/StringBuilder/StringBuilder()|",
      "|java+method:///net/fortuna/ical4j/data/CalendarBuilder/build(java.io.InputStream)|",
      "|java+method:///java/lang/Integer/parseInt(java.lang.String)|",
      "|java+method:///net/fortuna/ical4j/model/Calendar/getComponent(java.lang.String)|",
      "|java+constructor:///net/fortuna/ical4j/data/CalendarBuilder/CalendarBuilder()|",
      "|java+method:///net/fortuna/ical4j/model/property/TzUrl/getUri()|",
      "|java+method:///net/fortuna/ical4j/model/component/VTimeZone/getTimeZoneId()|",
      "|java+method:///java/lang/StringBuilder/toString()|",
      "|java+method:///net/fortuna/ical4j/util/Configurator/getProperty(java.lang.String)|",
      "|java+method:///java/net/URL/openConnection()|",
      "|java+method:///java/net/URLConnection/setConnectTimeout(int)|",
      "|java+method:///org/slf4j/Logger/warn(java.lang.String,java.lang.Throwable)|",
      "|java+method:///java/net/URI/toURL()|",
      "|java+method:///org/slf4j/LoggerFactory/getLogger(java.lang.Class)|",
      "|java+method:///java/net/URLConnection/getInputStream()|",
      "|java+method:///java/net/URLConnection/setReadTimeout(int)|",
      "|java+method:///java/lang/String/equals(java.lang.Object)|",
      "|java+method:///java/net/URL/openConnection(java.net.Proxy)|"
    ],
    "affectedLib": "org.slf4j:jcl-over-slf4j:1.7.7",
    "change": "REMOVED"
  },
  {
    "coordinatesV1": "org.mnode.ical4j:ical4j:2.0-alpha1",
    "coordinatesV2": "org.mnode.ical4j:ical4j:2.0-beta1",
    "caller": "|java+constructor:///net/fortuna/ical4j/model/Recur/Recur(java.lang.String,int)|",
    "called": "|java+method:///org/slf4j/LoggerFactory/getLogger(java.lang.Class)|",
    "v1Body": [
      "|java+method:///net/fortuna/ical4j/model/Recur/validateFrequency()|",
      "|java+constructor:///java/util/HashMap/HashMap()|",
      "|java+constructor:///java/lang/Object/Object()|",
      "|java+method:///org/apache/commons/logging/LogFactory/getLog(java.lang.Class)|"
    ],
    "v2Body": [
      "|java+method:///net/fortuna/ical4j/model/Recur/validateFrequency()|",
      "|java+method:///org/slf4j/LoggerFactory/getLogger(java.lang.Class)|",
      "|java+constructor:///java/util/HashMap/HashMap()|",
      "|java+constructor:///java/lang/Object/Object()|"
    ],
    "affectedLib": "org.slf4j:slf4j-api:1.7.10",
    "change": "ADDED"
  },
  {
    "coordinatesV1": "org.mnode.ical4j:ical4j:2.0-alpha1",
    "coordinatesV2": "org.mnode.ical4j:ical4j:2.0-beta1",
    "caller": "|java+method:///net/fortuna/ical4j/filter/Filter/filter(java.lang.Object%5B%5D)|",
    "called": "|java+method:///org/slf4j/LoggerFactory/getLogger(java.lang.Class)|",
    "v1Body": [
      "|java+method:///net/fortuna/ical4j/filter/Filter/filter(java.util.Collection)|",
      "|java+method:///java/lang/reflect/Array/newInstance(java.lang.Class,int)|",
      "|java+method:///java/util/Arrays/asList(java.lang.Object%5B%5D)|",
      "|java+method:///java/util/Collection/size()|",
      "|java+method:///java/util/Collection/toArray(java.lang.Object%5B%5D)|",
      "|java+method:///java/lang/Object/getClass()|",
      "|java+method:///org/apache/commons/logging/LogFactory/getLog(java.lang.Class)|",
      "|java+method:///org/apache/commons/logging/Log/warn(java.lang.Object,java.lang.Throwable)|",
      "|java+method:///java/util/Collection/toArray()|"
    ],
    "v2Body": [
      "|java+method:///org/slf4j/Logger/warn(java.lang.String,java.lang.Throwable)|",
      "|java+method:///net/fortuna/ical4j/filter/Filter/filter(java.util.Collection)|",
      "|java+method:///java/util/Collection/toArray()|",
      "|java+method:///java/lang/reflect/Array/newInstance(java.lang.Class,int)|",
      "|java+method:///java/util/Collection/size()|",
      "|java+method:///java/util/Collection/toArray(java.lang.Object%5B%5D)|",
      "|java+method:///java/lang/Object/getClass()|",
      "|java+method:///java/util/Arrays/asList(java.lang.Object%5B%5D)|",
      "|java+method:///org/slf4j/LoggerFactory/getLogger(java.lang.Class)|"
    ],
    "affectedLib": "org.slf4j:slf4j-api:1.7.10",
    "change": "ADDED"
  },
  {
    "coordinatesV1": "org.mnode.ical4j:ical4j:2.0-alpha1",
    "coordinatesV2": "org.mnode.ical4j:ical4j:2.0-beta1",
    "caller": "|java+constructor:///net/fortuna/ical4j/model/Recur/Recur()|",
    "called": "|java+method:///org/slf4j/LoggerFactory/getLogger(java.lang.Class)|",
    "v1Body": [
      "|java+constructor:///java/util/HashMap/HashMap()|",
      "|java+constructor:///java/lang/Object/Object()|",
      "|java+method:///org/apache/commons/logging/LogFactory/getLog(java.lang.Class)|"
    ],
    "v2Body": [
      "|java+method:///org/slf4j/LoggerFactory/getLogger(java.lang.Class)|",
      "|java+constructor:///java/util/HashMap/HashMap()|",
      "|java+constructor:///java/lang/Object/Object()|"
    ],
    "affectedLib": "org.slf4j:slf4j-api:1.7.10",
    "change": "ADDED"
  },
  {
    "coordinatesV1": "org.mnode.ical4j:ical4j:2.0-alpha1",
    "coordinatesV2": "org.mnode.ical4j:ical4j:2.0-beta1",
    "caller": "|java+constructor:///net/fortuna/ical4j/model/Recur/Recur(java.lang.String)|",
    "called": "|java+method:///org/slf4j/LoggerFactory/getLogger(java.lang.Class)|",
    "v1Body": [
      "|java+method:///java/util/Map/put(java.lang.Object,java.lang.Object)|",
      "|java+constructor:///net/fortuna/ical4j/model/WeekDayList/WeekDayList(java.lang.String)|",
      "|java+method:///net/fortuna/ical4j/model/DateTime/setUtc(boolean)|",
      "|java+constructor:///net/fortuna/ical4j/model/WeekDay/WeekDay(java.lang.String)|",
      "|java+method:///java/lang/String/format(java.lang.String,java.lang.Object%5B%5D)|",
      "|java+constructor:///java/util/HashMap/HashMap()|",
      "|java+method:///java/lang/String/equals(java.lang.Object)|",
      "|java+constructor:///net/fortuna/ical4j/model/NumberList/NumberList(java.lang.String,int,int,boolean)|",
      "|java+method:///java/lang/Integer/parseInt(java.lang.String)|",
      "|java+method:///java/lang/String/contains(java.lang.CharSequence)|",
      "|java+method:///java/util/StringTokenizer/hasMoreTokens()|",
      "|java+method:///net/fortuna/ical4j/model/Recur/nextToken(java.util.StringTokenizer,java.lang.String)|",
      "|java+method:///net/fortuna/ical4j/model/Recur/validateFrequency()|",
      "|java+constructor:///java/util/StringTokenizer/StringTokenizer(java.lang.String,java.lang.String)|",
      "|java+method:///net/fortuna/ical4j/model/WeekDay/getCalendarDay(net.fortuna.ical4j.model.WeekDay)|",
      "|java+method:///net/fortuna/ical4j/util/CompatibilityHints/isHintEnabled(java.lang.String)|",
      "|java+constructor:///net/fortuna/ical4j/model/Date/Date(java.lang.String)|",
      "|java+constructor:///net/fortuna/ical4j/model/DateTime/DateTime(java.lang.String)|",
      "|java+constructor:///java/lang/IllegalArgumentException/IllegalArgumentException(java.lang.String)|",
      "|java+method:///java/util/StringTokenizer/nextToken()|",
      "|java+constructor:///java/lang/Object/Object()|",
      "|java+method:///org/apache/commons/logging/LogFactory/getLog(java.lang.Class)|"
    ],
    "v2Body": [
      "|java+method:///java/util/Map/put(java.lang.Object,java.lang.Object)|",
      "|java+constructor:///net/fortuna/ical4j/model/WeekDayList/WeekDayList(java.lang.String)|",
      "|java+method:///net/fortuna/ical4j/model/DateTime/setUtc(boolean)|",
      "|java+constructor:///net/fortuna/ical4j/model/WeekDay/WeekDay(java.lang.String)|",
      "|java+method:///org/slf4j/LoggerFactory/getLogger(java.lang.Class)|",
      "|java+method:///java/lang/String/format(java.lang.String,java.lang.Object%5B%5D)|",
      "|java+constructor:///java/util/HashMap/HashMap()|",
      "|java+method:///java/lang/String/equals(java.lang.Object)|",
      "|java+constructor:///net/fortuna/ical4j/model/NumberList/NumberList(java.lang.String,int,int,boolean)|",
      "|java+method:///java/lang/Integer/parseInt(java.lang.String)|",
      "|java+method:///java/lang/String/contains(java.lang.CharSequence)|",
      "|java+method:///java/util/StringTokenizer/hasMoreTokens()|",
      "|java+method:///net/fortuna/ical4j/model/Recur/nextToken(java.util.StringTokenizer,java.lang.String)|",
      "|java+constructor:///java/lang/Object/Object()|",
      "|java+method:///net/fortuna/ical4j/model/Recur/validateFrequency()|",
      "|java+constructor:///java/util/StringTokenizer/StringTokenizer(java.lang.String,java.lang.String)|",
      "|java+method:///net/fortuna/ical4j/model/WeekDay/getCalendarDay(net.fortuna.ical4j.model.WeekDay)|",
      "|java+method:///net/fortuna/ical4j/util/CompatibilityHints/isHintEnabled(java.lang.String)|",
      "|java+constructor:///net/fortuna/ical4j/model/Date/Date(java.lang.String)|",
      "|java+constructor:///net/fortuna/ical4j/model/DateTime/DateTime(java.lang.String)|",
      "|java+constructor:///java/lang/IllegalArgumentException/IllegalArgumentException(java.lang.String)|",
      "|java+method:///java/util/StringTokenizer/nextToken()|"
    ],
    "affectedLib": "org.slf4j:slf4j-api:1.7.10",
    "change": "ADDED"
  },
  {
    "coordinatesV1": "org.mnode.ical4j:ical4j:2.0-alpha1",
    "coordinatesV2": "org.mnode.ical4j:ical4j:2.0-beta1",
    "caller": "|java+constructor:///net/fortuna/ical4j/model/Recur/Recur(java.lang.String,net.fortuna.ical4j.model.Date)|",
    "called": "|java+method:///org/slf4j/LoggerFactory/getLogger(java.lang.Class)|",
    "v1Body": [
      "|java+method:///net/fortuna/ical4j/model/Recur/validateFrequency()|",
      "|java+constructor:///java/util/HashMap/HashMap()|",
      "|java+constructor:///java/lang/Object/Object()|",
      "|java+method:///org/apache/commons/logging/LogFactory/getLog(java.lang.Class)|"
    ],
    "v2Body": [
      "|java+method:///net/fortuna/ical4j/model/Recur/validateFrequency()|",
      "|java+method:///org/slf4j/LoggerFactory/getLogger(java.lang.Class)|",
      "|java+constructor:///java/util/HashMap/HashMap()|",
      "|java+constructor:///java/lang/Object/Object()|"
    ],
    "affectedLib": "org.slf4j:slf4j-api:1.7.10",
    "change": "ADDED"
  },
  {
    "coordinatesV1": "org.mnode.ical4j:ical4j:2.0-alpha1",
    "coordinatesV2": "org.mnode.ical4j:ical4j:2.0-beta1",
    "caller": "|java+initializer:///net/fortuna/ical4j/data/HCalendarParser/HCalendarParser$initializer|",
    "called": "|java+method:///org/slf4j/LoggerFactory/getLogger(java.lang.Class)|",
    "v1Body": [
      "|java+method:///net/fortuna/ical4j/data/HCalendarParser/compileExpression(java.lang.String)|",
      "|java+method:///javax/xml/xpath/XPathFactory/newInstance()|",
      "|java+method:///javax/xml/parsers/DocumentBuilderFactory/newInstance()|",
      "|java+method:///org/apache/commons/logging/LogFactory/getLog(java.lang.Class)|",
      "|java+constructor:///java/text/SimpleDateFormat/SimpleDateFormat(java.lang.String)|",
      "|java+method:///javax/xml/parsers/DocumentBuilderFactory/setNamespaceAware(boolean)|",
      "|java+method:///javax/xml/xpath/XPathFactory/newXPath()|",
      "|java+method:///javax/xml/parsers/DocumentBuilderFactory/setIgnoringComments(boolean)|"
    ],
    "v2Body": [
      "|java+method:///net/fortuna/ical4j/data/HCalendarParser/compileExpression(java.lang.String)|",
      "|java+method:///org/slf4j/LoggerFactory/getLogger(java.lang.Class)|",
      "|java+method:///javax/xml/xpath/XPathFactory/newInstance()|",
      "|java+method:///javax/xml/parsers/DocumentBuilderFactory/newInstance()|",
      "|java+constructor:///java/text/SimpleDateFormat/SimpleDateFormat(java.lang.String)|",
      "|java+method:///javax/xml/parsers/DocumentBuilderFactory/setNamespaceAware(boolean)|",
      "|java+method:///javax/xml/xpath/XPathFactory/newXPath()|",
      "|java+method:///javax/xml/parsers/DocumentBuilderFactory/setIgnoringComments(boolean)|"
    ],
    "affectedLib": "org.slf4j:slf4j-api:1.7.10",
    "change": "ADDED"
  },
  {
    "coordinatesV1": "org.mnode.ical4j:ical4j:2.0-alpha1",
    "coordinatesV2": "org.mnode.ical4j:ical4j:2.0-beta1",
    "caller": "|java+method:///net/fortuna/ical4j/data/CalendarBuilder/updateTimeZone(net.fortuna.ical4j.model.Property,net.fortuna.ical4j.model.TimeZone)|",
    "called": "|java+method:///org/slf4j/LoggerFactory/getLogger(java.lang.Class)|",
    "v1Body": [
      "|java+method:///org/apache/commons/logging/Log/warn(java.lang.Object,java.lang.Throwable)|",
      "|java+method:///java/lang/StringBuilder/append(java.lang.String)|",
      "|java+method:///net/fortuna/ical4j/model/property/DateProperty/setTimeZone(net.fortuna.ical4j.model.TimeZone)|",
      "|java+method:///net/fortuna/ical4j/model/property/DateListProperty/setTimeZone(net.fortuna.ical4j.model.TimeZone)|",
      "|java+method:///net/fortuna/ical4j/model/TimeZone/getID()|",
      "|java+method:///net/fortuna/ical4j/util/CompatibilityHints/isHintEnabled(java.lang.String)|",
      "|java+constructor:///java/lang/StringBuilder/StringBuilder()|",
      "|java+method:///net/fortuna/ical4j/model/Property/getName()|",
      "|java+method:///org/apache/commons/logging/LogFactory/getLog(java.lang.Class)|",
      "|java+method:///java/lang/StringBuilder/toString()|"
    ],
    "v2Body": [
      "|java+method:///org/slf4j/Logger/warn(java.lang.String,java.lang.Throwable)|",
      "|java+method:///java/lang/StringBuilder/append(java.lang.String)|",
      "|java+method:///net/fortuna/ical4j/model/property/DateProperty/setTimeZone(net.fortuna.ical4j.model.TimeZone)|",
      "|java+method:///net/fortuna/ical4j/model/TimeZone/getID()|",
      "|java+method:///net/fortuna/ical4j/util/CompatibilityHints/isHintEnabled(java.lang.String)|",
      "|java+constructor:///java/lang/StringBuilder/StringBuilder()|",
      "|java+method:///net/fortuna/ical4j/model/Property/getName()|",
      "|java+method:///java/lang/StringBuilder/toString()|",
      "|java+method:///net/fortuna/ical4j/model/property/DateListProperty/setTimeZone(net.fortuna.ical4j.model.TimeZone)|",
      "|java+method:///org/slf4j/LoggerFactory/getLogger(java.lang.Class)|"
    ],
    "affectedLib": "org.slf4j:slf4j-api:1.7.10",
    "change": "ADDED"
  },
  {
    "coordinatesV1": "org.mnode.ical4j:ical4j:2.0-alpha1",
    "coordinatesV2": "org.mnode.ical4j:ical4j:2.0-beta1",
    "caller": "|java+method:///net/fortuna/ical4j/model/property/Attach/getValue()|",
    "called": "|java+method:///org/slf4j/LoggerFactory/getLogger(java.lang.Class)|",
    "v1Body": [
      "|java+method:///net/fortuna/ical4j/util/EncoderFactory/getInstance()|",
      "|java+method:///net/fortuna/ical4j/util/EncoderFactory/createBinaryEncoder(net.fortuna.ical4j.model.parameter.Encoding)|",
      "|java+method:///net/fortuna/ical4j/util/Strings/valueOf(java.lang.Object)|",
      "|java+method:///net/fortuna/ical4j/model/property/Attach/getBinary()|",
      "|java+method:///org/apache/commons/codec/BinaryEncoder/encode(byte%5B%5D)|",
      "|java+constructor:///java/lang/String/String(byte%5B%5D)|",
      "|java+method:///org/apache/commons/logging/Log/error(java.lang.Object,java.lang.Throwable)|",
      "|java+method:///net/fortuna/ical4j/model/property/Attach/getUri()|",
      "|java+method:///org/apache/commons/logging/LogFactory/getLog(java.lang.Class)|",
      "|java+method:///net/fortuna/ical4j/model/property/Attach/getParameter(java.lang.String)|",
      "|java+method:///net/fortuna/ical4j/util/Uris/decode(java.lang.String)|"
    ],
    "v2Body": [
      "|java+method:///net/fortuna/ical4j/util/EncoderFactory/getInstance()|",
      "|java+method:///net/fortuna/ical4j/util/EncoderFactory/createBinaryEncoder(net.fortuna.ical4j.model.parameter.Encoding)|",
      "|java+method:///net/fortuna/ical4j/util/Strings/valueOf(java.lang.Object)|",
      "|java+method:///net/fortuna/ical4j/model/property/Attach/getBinary()|",
      "|java+method:///org/slf4j/LoggerFactory/getLogger(java.lang.Class)|",
      "|java+method:///org/apache/commons/codec/BinaryEncoder/encode(byte%5B%5D)|",
      "|java+constructor:///java/lang/String/String(byte%5B%5D)|",
      "|java+method:///org/slf4j/Logger/error(java.lang.String,java.lang.Throwable)|",
      "|java+method:///net/fortuna/ical4j/model/property/Attach/getUri()|",
      "|java+method:///net/fortuna/ical4j/model/property/Attach/getParameter(java.lang.String)|",
      "|java+method:///net/fortuna/ical4j/util/Uris/decode(java.lang.String)|"
    ],
    "affectedLib": "org.slf4j:slf4j-api:1.7.10",
    "change": "ADDED"
  },
  {
    "coordinatesV1": "org.mnode.ical4j:ical4j:2.0-alpha1",
    "coordinatesV2": "org.mnode.ical4j:ical4j:2.0-beta1",
    "caller": "|java+constructor:///net/fortuna/ical4j/data/UnfoldingReader/UnfoldingReader(java.io.Reader,int,boolean)|",
    "called": "|java+method:///org/slf4j/LoggerFactory/getLogger(java.lang.Class)|",
    "v1Body": [
      "|java+method:///java/lang/Math/max(int,int)|",
      "|java+constructor:///java/io/PushbackReader/PushbackReader(java.io.Reader,int)|",
      "|java+method:///org/apache/commons/logging/LogFactory/getLog(java.lang.Class)|"
    ],
    "v2Body": [
      "|java+method:///java/lang/Math/max(int,int)|",
      "|java+method:///org/slf4j/LoggerFactory/getLogger(java.lang.Class)|",
      "|java+constructor:///java/io/PushbackReader/PushbackReader(java.io.Reader,int)|"
    ],
    "affectedLib": "org.slf4j:slf4j-api:1.7.10",
    "change": "ADDED"
  },
  {
    "coordinatesV1": "org.mnode.ical4j:ical4j:2.0-alpha1",
    "coordinatesV2": "org.mnode.ical4j:ical4j:2.0-beta1",
    "caller": "|java+method:///net/fortuna/ical4j/model/TimeZoneRegistryImpl/getTimeZone(java.lang.String)|",
    "called": "|java+method:///org/slf4j/LoggerFactory/getLogger(java.lang.Class)|",
    "v1Body": [
      "|java+method:///java/util/Map/put(java.lang.Object,java.lang.Object)|",
      "|java+method:///net/fortuna/ical4j/model/TimeZoneRegistryImpl/getTimeZone(java.lang.String)|",
      "|java+method:///java/util/Properties/getProperty(java.lang.String)|",
      "|java+method:///org/apache/commons/logging/Log/warn(java.lang.Object,java.lang.Throwable)|",
      "|java+method:///java/util/Map/get(java.lang.Object)|",
      "|java+method:///net/fortuna/ical4j/model/TimeZone/getID()|",
      "|java+method:///net/fortuna/ical4j/util/CompatibilityHints/isHintEnabled(java.lang.String)|",
      "|java+constructor:///net/fortuna/ical4j/model/TimeZone/TimeZone(net.fortuna.ical4j.model.component.VTimeZone)|",
      "|java+method:///java/util/regex/Matcher/group()|",
      "|java+method:///java/util/regex/Matcher/find()|",
      "|java+method:///java/util/regex/Pattern/matcher(java.lang.CharSequence)|",
      "|java+method:///net/fortuna/ical4j/model/TimeZoneRegistryImpl/loadVTimeZone(java.lang.String)|",
      "|java+method:///org/apache/commons/logging/LogFactory/getLog(java.lang.Class)|"
    ],
    "v2Body": [
      "|java+method:///java/util/Map/put(java.lang.Object,java.lang.Object)|",
      "|java+method:///net/fortuna/ical4j/model/TimeZoneRegistryImpl/getTimeZone(java.lang.String)|",
      "|java+method:///java/util/Properties/getProperty(java.lang.String)|",
      "|java+method:///org/slf4j/Logger/warn(java.lang.String,java.lang.Throwable)|",
      "|java+method:///net/fortuna/ical4j/model/TimeZone/getID()|",
      "|java+method:///net/fortuna/ical4j/util/CompatibilityHints/isHintEnabled(java.lang.String)|",
      "|java+constructor:///net/fortuna/ical4j/model/TimeZone/TimeZone(net.fortuna.ical4j.model.component.VTimeZone)|",
      "|java+method:///java/util/regex/Matcher/group()|",
      "|java+method:///java/util/regex/Matcher/find()|",
      "|java+method:///java/util/regex/Pattern/matcher(java.lang.CharSequence)|",
      "|java+method:///net/fortuna/ical4j/model/TimeZoneRegistryImpl/loadVTimeZone(java.lang.String)|",
      "|java+method:///java/util/Map/get(java.lang.Object)|",
      "|java+method:///org/slf4j/LoggerFactory/getLogger(java.lang.Class)|"
    ],
    "affectedLib": "org.slf4j:slf4j-api:1.7.10",
    "change": "ADDED"
  },
  {
    "coordinatesV1": "org.mnode.ical4j:ical4j:2.0-alpha1",
    "coordinatesV2": "org.mnode.ical4j:ical4j:2.0-beta1",
    "caller": "|java+initializer:///net/fortuna/ical4j/model/TimeZoneRegistryImpl/TimeZoneRegistryImpl$initializer|",
    "called": "|java+method:///org/slf4j/LoggerFactory/getLogger(java.lang.Class)|",
    "v1Body": [
      "|java+method:///org/apache/commons/logging/Log/debug(java.lang.Object)|",
      "|java+method:///java/util/regex/Pattern/compile(java.lang.String)|",
      "|java+method:///org/apache/commons/logging/Log/warn(java.lang.Object)|",
      "|java+method:///java/io/IOException/getMessage()|",
      "|java+constructor:///java/util/Properties/Properties()|",
      "|java+constructor:///java/lang/StringBuilder/StringBuilder()|",
      "|java+method:///org/apache/commons/logging/LogFactory/getLog(java.lang.Class)|",
      "|java+method:///java/lang/StringBuilder/append(java.lang.String)|",
      "|java+constructor:///java/util/concurrent/ConcurrentHashMap/ConcurrentHashMap()|",
      "|java+method:///net/fortuna/ical4j/util/ResourceLoader/getResourceAsStream(java.lang.String)|",
      "|java+method:///java/util/Properties/load(java.io.InputStream)|",
      "|java+method:///java/lang/StringBuilder/toString()|",
      "|java+method:///java/lang/Exception/getMessage()|"
    ],
    "v2Body": [
      "|java+method:///org/slf4j/Logger/debug(java.lang.String)|",
      "|java+method:///java/io/IOException/getMessage()|",
      "|java+method:///java/lang/Throwable/getMessage()|",
      "|java+method:///java/io/InputStream/close()|",
      "|java+constructor:///java/lang/StringBuilder/StringBuilder()|",
      "|java+method:///java/lang/Integer/parseInt(java.lang.String)|",
      "|java+method:///net/fortuna/ical4j/util/Configurator/getProperty(java.lang.String)|",
      "|java+method:///java/util/regex/Pattern/compile(java.lang.String)|",
      "|java+constructor:///java/net/InetSocketAddress/InetSocketAddress(java.lang.String,int)|",
      "|java+method:///org/slf4j/Logger/warn(java.lang.String)|",
      "|java+method:///java/lang/StringBuilder/append(java.lang.String)|",
      "|java+constructor:///java/util/concurrent/ConcurrentHashMap/ConcurrentHashMap()|",
      "|java+constructor:///java/net/Proxy/Proxy(java.net.Proxy$Type,java.net.SocketAddress)|",
      "|java+method:///org/slf4j/LoggerFactory/getLogger(java.lang.Class)|",
      "|java+method:///java/lang/String/equals(java.lang.Object)|",
      "|java+constructor:///java/util/Properties/Properties()|",
      "|java+method:///net/fortuna/ical4j/util/ResourceLoader/getResourceAsStream(java.lang.String)|",
      "|java+method:///java/util/Properties/load(java.io.InputStream)|",
      "|java+method:///java/lang/StringBuilder/toString()|",
      "|java+method:///java/lang/Exception/getMessage()|",
      "|java+method:///java/net/Proxy$Type/valueOf(java.lang.String)|"
    ],
    "affectedLib": "org.slf4j:slf4j-api:1.7.10",
    "change": "ADDED"
  },
  {
    "coordinatesV1": "org.mnode.ical4j:ical4j:2.0-alpha1",
    "coordinatesV2": "org.mnode.ical4j:ical4j:2.0-beta1",
    "caller": "|java+constructor:///net/fortuna/ical4j/data/FoldingWriter/FoldingWriter(java.io.Writer,int)|",
    "called": "|java+method:///org/slf4j/LoggerFactory/getLogger(java.lang.Class)|",
    "v1Body": [
      "|java+constructor:///java/io/FilterWriter/FilterWriter(java.io.Writer)|",
      "|java+method:///java/lang/Math/min(int,int)|",
      "|java+method:///org/apache/commons/logging/LogFactory/getLog(java.lang.Class)|"
    ],
    "v2Body": [
      "|java+constructor:///java/io/FilterWriter/FilterWriter(java.io.Writer)|",
      "|java+method:///org/slf4j/LoggerFactory/getLogger(java.lang.Class)|",
      "|java+method:///java/lang/Math/min(int,int)|"
    ],
    "affectedLib": "org.slf4j:slf4j-api:1.7.10",
    "change": "ADDED"
  },
  {
    "coordinatesV1": "org.mnode.ical4j:ical4j:2.0-alpha1",
    "coordinatesV2": "org.mnode.ical4j:ical4j:2.0-beta1",
    "caller": "|java+method:///net/fortuna/ical4j/model/component/Observance/getLatestOnset(net.fortuna.ical4j.model.Date)|",
    "called": "|java+method:///org/slf4j/LoggerFactory/getLogger(java.lang.Class)|",
    "v1Body": [
      "|java+method:///net/fortuna/ical4j/model/DateTime/getTime()|",
      "|java+method:///net/fortuna/ical4j/util/Dates/getCalendarInstance(net.fortuna.ical4j.model.Date)|",
      "|java+method:///java/util/Iterator/hasNext()|",
      "|java+method:///net/fortuna/ical4j/model/DateList/size()|",
      "|java+method:///java/util/Iterator/next()|",
      "|java+method:///net/fortuna/ical4j/model/component/Observance/getProperties(java.lang.String)|",
      "|java+method:///net/fortuna/ical4j/model/component/Observance/getProperty(java.lang.String)|",
      "|java+method:///java/util/Collections/sort(java.util.List)|",
      "|java+method:///org/apache/commons/logging/Log/error(java.lang.Object,java.lang.Throwable)|",
      "|java+constructor:///net/fortuna/ical4j/model/DateList/DateList()|",
      "|java+method:///org/apache/commons/logging/LogFactory/getLog(java.lang.Class)|",
      "|java+method:///net/fortuna/ical4j/model/property/DtStart/getDate()|",
      "|java+method:///java/util/Calendar/setTime(java.util.Date)|",
      "|java+method:///java/util/Calendar/add(int,int)|",
      "|java+method:///java/util/Calendar/getTime()|",
      "|java+method:///net/fortuna/ical4j/model/DateTime/after(java.util.Date)|",
      "|java+method:///net/fortuna/ical4j/model/component/Observance/getCachedOnset(net.fortuna.ical4j.model.Date)|",
      "|java+method:///net/fortuna/ical4j/model/PropertyList/iterator()|",
      "|java+method:///net/fortuna/ical4j/model/DateList/add(net.fortuna.ical4j.model.Date)|",
      "|java+method:///net/fortuna/ical4j/model/DateList/get(int)|",
      "|java+method:///net/fortuna/ical4j/util/Dates/getInstance(java.util.Date,net.fortuna.ical4j.model.parameter.Value)|",
      "|java+method:///net/fortuna/ical4j/model/DateList/setUtc(boolean)|",
      "|java+method:///net/fortuna/ical4j/model/DateList/iterator()|",
      "|java+method:///net/fortuna/ical4j/model/Date/before(java.util.Date)|",
      "|java+method:///net/fortuna/ical4j/model/property/RRule/getRecur()|",
      "|java+method:///net/fortuna/ical4j/model/component/Observance/calculateOnset(net.fortuna.ical4j.model.Date)|",
      "|java+method:///net/fortuna/ical4j/model/property/RDate/getDates()|",
      "|java+method:///net/fortuna/ical4j/model/Recur/getDates(net.fortuna.ical4j.model.Date,net.fortuna.ical4j.model.Date,net.fortuna.ical4j.model.parameter.Value)|",
      "|java+method:///net/fortuna/ical4j/model/component/Observance/applyOffsetFrom(net.fortuna.ical4j.model.DateTime)|"
    ],
    "v2Body": [
      "|java+method:///net/fortuna/ical4j/model/DateTime/getTime()|",
      "|java+method:///net/fortuna/ical4j/util/Dates/getCalendarInstance(net.fortuna.ical4j.model.Date)|",
      "|java+method:///java/util/Iterator/hasNext()|",
      "|java+method:///net/fortuna/ical4j/model/DateList/size()|",
      "|java+method:///java/util/Iterator/next()|",
      "|java+method:///net/fortuna/ical4j/model/component/Observance/getProperties(java.lang.String)|",
      "|java+method:///net/fortuna/ical4j/model/component/Observance/getProperty(java.lang.String)|",
      "|java+method:///java/util/Collections/sort(java.util.List)|",
      "|java+constructor:///net/fortuna/ical4j/model/DateList/DateList()|",
      "|java+method:///net/fortuna/ical4j/model/property/DtStart/getDate()|",
      "|java+method:///java/util/Calendar/setTime(java.util.Date)|",
      "|java+method:///java/util/Calendar/add(int,int)|",
      "|java+method:///java/util/Calendar/getTime()|",
      "|java+method:///org/slf4j/LoggerFactory/getLogger(java.lang.Class)|",
      "|java+method:///net/fortuna/ical4j/model/DateTime/after(java.util.Date)|",
      "|java+method:///net/fortuna/ical4j/model/component/Observance/getCachedOnset(net.fortuna.ical4j.model.Date)|",
      "|java+method:///net/fortuna/ical4j/model/PropertyList/iterator()|",
      "|java+method:///net/fortuna/ical4j/model/DateList/add(net.fortuna.ical4j.model.Date)|",
      "|java+method:///net/fortuna/ical4j/model/DateList/get(int)|",
      "|java+method:///net/fortuna/ical4j/util/Dates/getInstance(java.util.Date,net.fortuna.ical4j.model.parameter.Value)|",
      "|java+method:///org/slf4j/Logger/error(java.lang.String,java.lang.Throwable)|",
      "|java+method:///net/fortuna/ical4j/model/DateList/setUtc(boolean)|",
      "|java+method:///net/fortuna/ical4j/model/DateList/iterator()|",
      "|java+method:///net/fortuna/ical4j/model/Date/before(java.util.Date)|",
      "|java+method:///net/fortuna/ical4j/model/property/RRule/getRecur()|",
      "|java+method:///net/fortuna/ical4j/model/component/Observance/calculateOnset(net.fortuna.ical4j.model.Date)|",
      "|java+method:///net/fortuna/ical4j/model/property/RDate/getDates()|",
      "|java+method:///net/fortuna/ical4j/model/Recur/getDates(net.fortuna.ical4j.model.Date,net.fortuna.ical4j.model.Date,net.fortuna.ical4j.model.parameter.Value)|",
      "|java+method:///net/fortuna/ical4j/model/component/Observance/applyOffsetFrom(net.fortuna.ical4j.model.DateTime)|"
    ],
    "affectedLib": "org.slf4j:slf4j-api:1.7.10",
    "change": "ADDED"
  },
  {
    "coordinatesV1": "org.mnode.ical4j:ical4j:2.0-alpha1",
    "coordinatesV2": "org.mnode.ical4j:ical4j:2.0-beta1",
    "caller": "|java+initializer:///net/fortuna/ical4j/util/ResourceLoader/ResourceLoader$initializer|",
    "called": "|java+method:///org/slf4j/LoggerFactory/getLogger(java.lang.Class)|",
    "v1Body": [
      "|java+method:///org/apache/commons/logging/LogFactory/getLog(java.lang.Class)|"
    ],
    "v2Body": [
      "|java+method:///org/slf4j/LoggerFactory/getLogger(java.lang.Class)|"
    ],
    "affectedLib": "org.slf4j:slf4j-api:1.7.10",
    "change": "ADDED"
  },
  {
    "coordinatesV1": "org.mnode.ical4j:ical4j:2.0-alpha1",
    "coordinatesV2": "org.mnode.ical4j:ical4j:2.0-beta1",
    "caller": "|java+method:///net/fortuna/ical4j/model/Recur/readObject(java.io.ObjectInputStream)|",
    "called": "|java+method:///org/slf4j/LoggerFactory/getLogger(java.lang.Class)|",
    "v1Body": [
      "|java+method:///java/io/ObjectInputStream/defaultReadObject()|",
      "|java+method:///org/apache/commons/logging/LogFactory/getLog(java.lang.Class)|"
    ],
    "v2Body": [
      "|java+method:///org/slf4j/LoggerFactory/getLogger(java.lang.Class)|",
      "|java+method:///java/io/ObjectInputStream/defaultReadObject()|"
    ],
    "affectedLib": "org.slf4j:slf4j-api:1.7.10",
    "change": "ADDED"
  },
  {
    "coordinatesV1": "org.mnode.ical4j:ical4j:2.0-alpha1",
    "coordinatesV2": "org.mnode.ical4j:ical4j:2.0-beta1",
    "caller": "|java+constructor:///net/fortuna/ical4j/data/CalendarParserImpl/CalendarParserImpl()|",
    "called": "|java+method:///org/slf4j/LoggerFactory/getLogger(java.lang.Class)|",
    "v1Body": [
      "|java+constructor:///net/fortuna/ical4j/data/CalendarParserImpl$PropertyParser/CalendarParserImpl$PropertyParser(net.fortuna.ical4j.data.CalendarParserImpl,net.fortuna.ical4j.data.CalendarParserImpl$1)|",
      "|java+constructor:///net/fortuna/ical4j/data/CalendarParserImpl$PropertyListParser/CalendarParserImpl$PropertyListParser(net.fortuna.ical4j.data.CalendarParserImpl,net.fortuna.ical4j.data.CalendarParserImpl$1)|",
      "|java+constructor:///net/fortuna/ical4j/data/CalendarParserImpl$ComponentParser/CalendarParserImpl$ComponentParser(net.fortuna.ical4j.data.CalendarParserImpl,net.fortuna.ical4j.data.CalendarParserImpl$1)|",
      "|java+constructor:///net/fortuna/ical4j/data/CalendarParserImpl$ParameterListParser/CalendarParserImpl$ParameterListParser(net.fortuna.ical4j.data.CalendarParserImpl,net.fortuna.ical4j.data.CalendarParserImpl$1)|",
      "|java+constructor:///java/lang/Object/Object()|",
      "|java+method:///org/apache/commons/logging/LogFactory/getLog(java.lang.Class)|",
      "|java+constructor:///net/fortuna/ical4j/data/CalendarParserImpl$ComponentListParser/CalendarParserImpl$ComponentListParser(net.fortuna.ical4j.data.CalendarParserImpl,net.fortuna.ical4j.data.CalendarParserImpl$1)|",
      "|java+constructor:///net/fortuna/ical4j/data/CalendarParserImpl$ParameterParser/CalendarParserImpl$ParameterParser(net.fortuna.ical4j.data.CalendarParserImpl,net.fortuna.ical4j.data.CalendarParserImpl$1)|"
    ],
    "v2Body": [
      "|java+constructor:///net/fortuna/ical4j/data/CalendarParserImpl$PropertyParser/CalendarParserImpl$PropertyParser(net.fortuna.ical4j.data.CalendarParserImpl,net.fortuna.ical4j.data.CalendarParserImpl$1)|",
      "|java+constructor:///net/fortuna/ical4j/data/CalendarParserImpl$PropertyListParser/CalendarParserImpl$PropertyListParser(net.fortuna.ical4j.data.CalendarParserImpl,net.fortuna.ical4j.data.CalendarParserImpl$1)|",
      "|java+method:///org/slf4j/LoggerFactory/getLogger(java.lang.Class)|",
      "|java+constructor:///net/fortuna/ical4j/data/CalendarParserImpl$ComponentParser/CalendarParserImpl$ComponentParser(net.fortuna.ical4j.data.CalendarParserImpl,net.fortuna.ical4j.data.CalendarParserImpl$1)|",
      "|java+constructor:///net/fortuna/ical4j/data/CalendarParserImpl$ParameterListParser/CalendarParserImpl$ParameterListParser(net.fortuna.ical4j.data.CalendarParserImpl,net.fortuna.ical4j.data.CalendarParserImpl$1)|",
      "|java+constructor:///java/lang/Object/Object()|",
      "|java+constructor:///net/fortuna/ical4j/data/CalendarParserImpl$ComponentListParser/CalendarParserImpl$ComponentListParser(net.fortuna.ical4j.data.CalendarParserImpl,net.fortuna.ical4j.data.CalendarParserImpl$1)|",
      "|java+constructor:///net/fortuna/ical4j/data/CalendarParserImpl$ParameterParser/CalendarParserImpl$ParameterParser(net.fortuna.ical4j.data.CalendarParserImpl,net.fortuna.ical4j.data.CalendarParserImpl$1)|"
    ],
    "affectedLib": "org.slf4j:slf4j-api:1.7.10",
    "change": "ADDED"
  },
  {
    "coordinatesV1": "org.mnode.ical4j:ical4j:2.0-alpha1",
    "coordinatesV2": "org.mnode.ical4j:ical4j:2.0-beta1",
    "caller": "|java+initializer:///net/fortuna/ical4j/model/CalendarDateFormatFactory/CalendarDateFormatFactory$initializer|",
    "called": "|java+method:///org/slf4j/LoggerFactory/getLogger(java.lang.Class)|",
    "v1Body": [
      "|java+method:///org/apache/commons/logging/LogFactory/getLog(java.lang.Class)|"
    ],
    "v2Body": [
      "|java+method:///org/slf4j/LoggerFactory/getLogger(java.lang.Class)|"
    ],
    "affectedLib": "org.slf4j:slf4j-api:1.7.10",
    "change": "ADDED"
  },
  {
    "coordinatesV1": "org.mnode.ical4j:ical4j:2.0-alpha1",
    "coordinatesV2": "org.mnode.ical4j:ical4j:2.0-beta1",
    "caller": "|java+initializer:///net/fortuna/ical4j/util/Configurator/Configurator$initializer|",
    "called": "|java+method:///org/slf4j/LoggerFactory/getLogger(java.lang.Class)|",
    "v1Body": [
      "|java+method:///org/apache/commons/logging/Log/info(java.lang.Object)|",
      "|java+constructor:///java/util/Properties/Properties()|",
      "|java+method:///org/apache/commons/logging/LogFactory/getLog(java.lang.Class)|",
      "|java+method:///net/fortuna/ical4j/util/ResourceLoader/getResourceAsStream(java.lang.String)|",
      "|java+method:///java/util/Properties/load(java.io.InputStream)|"
    ],
    "v2Body": [
      "|java+method:///org/slf4j/LoggerFactory/getLogger(java.lang.Class)|",
      "|java+method:///org/slf4j/Logger/info(java.lang.String)|",
      "|java+constructor:///java/util/Properties/Properties()|",
      "|java+method:///net/fortuna/ical4j/util/ResourceLoader/getResourceAsStream(java.lang.String)|",
      "|java+method:///java/util/Properties/load(java.io.InputStream)|"
    ],
    "affectedLib": "org.slf4j:slf4j-api:1.7.10",
    "change": "ADDED"
  },
  {
    "coordinatesV1": "org.mnode.ical4j:ical4j:2.0-alpha1",
    "coordinatesV2": "org.mnode.ical4j:ical4j:2.0-beta1",
    "caller": "|java+method:///net/fortuna/ical4j/model/property/Attach/setValue(java.lang.String)|",
    "called": "|java+method:///org/slf4j/LoggerFactory/getLogger(java.lang.Class)|",
    "v1Body": [
      "|java+method:///org/apache/commons/codec/BinaryDecoder/decode(byte%5B%5D)|",
      "|java+method:///net/fortuna/ical4j/util/DecoderFactory/createBinaryDecoder(net.fortuna.ical4j.model.parameter.Encoding)|",
      "|java+method:///net/fortuna/ical4j/model/property/Attach/getParameter(java.lang.String)|",
      "|java+method:///org/apache/commons/logging/Log/error(java.lang.Object,java.lang.Throwable)|",
      "|java+method:///net/fortuna/ical4j/util/DecoderFactory/getInstance()|",
      "|java+method:///java/lang/String/getBytes()|",
      "|java+method:///org/apache/commons/logging/LogFactory/getLog(java.lang.Class)|",
      "|java+method:///net/fortuna/ical4j/util/Uris/create(java.lang.String)|"
    ],
    "v2Body": [
      "|java+method:///org/apache/commons/codec/BinaryDecoder/decode(byte%5B%5D)|",
      "|java+method:///net/fortuna/ical4j/util/DecoderFactory/createBinaryDecoder(net.fortuna.ical4j.model.parameter.Encoding)|",
      "|java+method:///org/slf4j/LoggerFactory/getLogger(java.lang.Class)|",
      "|java+method:///net/fortuna/ical4j/model/property/Attach/getParameter(java.lang.String)|",
      "|java+method:///org/slf4j/Logger/error(java.lang.String,java.lang.Throwable)|",
      "|java+method:///net/fortuna/ical4j/util/DecoderFactory/getInstance()|",
      "|java+method:///java/lang/String/getBytes()|",
      "|java+method:///net/fortuna/ical4j/util/Uris/create(java.lang.String)|"
    ],
    "affectedLib": "org.slf4j:slf4j-api:1.7.10",
    "change": "ADDED"
  },
  {
    "coordinatesV1": "org.mnode.ical4j:ical4j:2.0-alpha1",
    "coordinatesV2": "org.mnode.ical4j:ical4j:2.0-beta1",
    "caller": "|java+method:///net/fortuna/ical4j/model/TimeZoneRegistryImpl/updateDefinition(net.fortuna.ical4j.model.component.VTimeZone)|",
    "called": "|java+method:///org/slf4j/LoggerFactory/getLogger(java.lang.Class)|",
    "v1Body": [
      "|java+method:///net/fortuna/ical4j/model/property/TzId/getValue()|",
      "|java+method:///net/fortuna/ical4j/model/component/VTimeZone/getTimeZoneUrl()|",
      "|java+method:///java/net/URL/openStream()|",
      "|java+method:///org/apache/commons/logging/Log/warn(java.lang.Object,java.lang.Throwable)|",
      "|java+method:///java/lang/StringBuilder/append(java.lang.String)|",
      "|java+method:///java/net/URI/toURL()|",
      "|java+constructor:///java/lang/StringBuilder/StringBuilder()|",
      "|java+method:///net/fortuna/ical4j/data/CalendarBuilder/build(java.io.InputStream)|",
      "|java+method:///net/fortuna/ical4j/model/Calendar/getComponent(java.lang.String)|",
      "|java+constructor:///net/fortuna/ical4j/data/CalendarBuilder/CalendarBuilder()|",
      "|java+method:///net/fortuna/ical4j/model/property/TzUrl/getUri()|",
      "|java+method:///net/fortuna/ical4j/model/component/VTimeZone/getTimeZoneId()|",
      "|java+method:///org/apache/commons/logging/LogFactory/getLog(java.lang.Class)|",
      "|java+method:///java/lang/StringBuilder/toString()|"
    ],
    "v2Body": [
      "|java+method:///net/fortuna/ical4j/model/property/TzId/getValue()|",
      "|java+method:///net/fortuna/ical4j/model/component/VTimeZone/getTimeZoneUrl()|",
      "|java+method:///java/lang/StringBuilder/append(java.lang.String)|",
      "|java+constructor:///java/lang/StringBuilder/StringBuilder()|",
      "|java+method:///net/fortuna/ical4j/data/CalendarBuilder/build(java.io.InputStream)|",
      "|java+method:///java/lang/Integer/parseInt(java.lang.String)|",
      "|java+method:///net/fortuna/ical4j/model/Calendar/getComponent(java.lang.String)|",
      "|java+constructor:///net/fortuna/ical4j/data/CalendarBuilder/CalendarBuilder()|",
      "|java+method:///net/fortuna/ical4j/model/property/TzUrl/getUri()|",
      "|java+method:///net/fortuna/ical4j/model/component/VTimeZone/getTimeZoneId()|",
      "|java+method:///java/lang/StringBuilder/toString()|",
      "|java+method:///net/fortuna/ical4j/util/Configurator/getProperty(java.lang.String)|",
      "|java+method:///java/net/URL/openConnection()|",
      "|java+method:///java/net/URLConnection/setConnectTimeout(int)|",
      "|java+method:///org/slf4j/Logger/warn(java.lang.String,java.lang.Throwable)|",
      "|java+method:///java/net/URI/toURL()|",
      "|java+method:///org/slf4j/LoggerFactory/getLogger(java.lang.Class)|",
      "|java+method:///java/net/URLConnection/getInputStream()|",
      "|java+method:///java/net/URLConnection/setReadTimeout(int)|",
      "|java+method:///java/lang/String/equals(java.lang.Object)|",
      "|java+method:///java/net/URL/openConnection(java.net.Proxy)|"
    ],
    "affectedLib": "org.slf4j:slf4j-api:1.7.10",
    "change": "ADDED"
  }
]