[
  {
    "coordinatesV1": "com.sandinh:scala-soap_2.11:1.3.0",
    "coordinatesV2": "com.sandinh:scala-soap_2.11:1.5.0",
    "caller": "|java+method:///com/sandinh/soap/SOAPDate$/apply(java.lang.String)|",
    "called": "|java+method:///org/joda/time/format/ISODateTimeFormat/dateHourMinuteSecond()|",
    "v1Body": [
      "|java+method:///com/sandinh/soap/SOAPDate$/longDateFormatter()|",
      "|java+constructor:///com/sandinh/soap/SOAPDate/SOAPDate(java.util.Date,java.text.DateFormat)|",
      "|java+method:///com/sandinh/soap/SOAPDate$/textToDate(java.lang.String)|"
    ],
    "v2Body": [
      "|java+constructor:///com/sandinh/soap/SOAPDate/SOAPDate(org.joda.time.DateTime,org.joda.time.format.DateTimeFormatter)|",
      "|java+method:///org/joda/time/format/ISODateTimeFormat/dateHourMinuteSecond()|",
      "|java+method:///com/sandinh/soap/SOAPDate$/textToDate(java.lang.String)|"
    ],
    "affectedLib": "joda-time:joda-time:2.9.1",
    "change": "ADDED"
  },
  {
    "coordinatesV1": "com.sandinh:scala-soap_2.11:1.3.0",
    "coordinatesV2": "com.sandinh:scala-soap_2.11:1.5.0",
    "caller": "|java+method:///com/sandinh/soap/SOAPDate$/textToDate(java.lang.String)|",
    "called": "|java+method:///org/joda/time/format/DateTimeFormatter/parseDateTime(java.lang.String)|",
    "v1Body": [
      "|java+method:///scala/collection/immutable/StringOps/size()|",
      "|java+method:///scala/Predef$/augmentString(java.lang.String)|",
      "|java+method:///com/sandinh/soap/SOAPDate$/shortDateFormatter()|",
      "|java+method:///scala/Predef$/wrapRefArray(java.lang.Object%5B%5D)|",
      "|java+method:///scala/Predef$/genericWrapArray(java.lang.Object)|",
      "|java+constructor:///java/lang/IllegalArgumentException/IllegalArgumentException(java.lang.String)|",
      "|java+constructor:///scala/collection/immutable/StringOps/StringOps(java.lang.String)|",
      "|java+method:///com/sandinh/soap/SOAPDate$/shortFormatTemplate()|",
      "|java+method:///scala/StringContext/s(scala.collection.Seq)|",
      "|java+method:///com/sandinh/soap/SOAPDate$/longDateFormatter()|",
      "|java+constructor:///scala/StringContext/StringContext(scala.collection.Seq)|",
      "|java+method:///com/sandinh/soap/SOAPDate$/longFormatTemplate()|",
      "|java+method:///java/text/DateFormat/parse(java.lang.String)|"
    ],
    "v2Body": [
      "|java+method:///org/joda/time/format/ISODateTimeFormat/yearMonthDay()|",
      "|java+method:///org/joda/time/format/ISODateTimeFormat/dateHourMinuteSecond()|",
      "|java+method:///org/joda/time/format/DateTimeFormatter/parseDateTime(java.lang.String)|",
      "|java+method:///java/lang/String/length()|"
    ],
    "affectedLib": "joda-time:joda-time:2.9.1",
    "change": "ADDED"
  },
  {
    "coordinatesV1": "com.sandinh:scala-soap_2.11:1.3.0",
    "coordinatesV2": "com.sandinh:scala-soap_2.11:1.5.0",
    "caller": "|java+method:///com/sandinh/soap/SOAPDate/toString()|",
    "called": "|java+method:///org/joda/time/format/DateTimeFormatter/print(org.joda.time.ReadableInstant)|",
    "v1Body": [
      "|java+method:///java/text/DateFormat/format(java.util.Date)|"
    ],
    "v2Body": [
      "|java+method:///org/joda/time/format/DateTimeFormatter/print(org.joda.time.ReadableInstant)|"
    ],
    "affectedLib": "joda-time:joda-time:2.9.1",
    "change": "ADDED"
  },
  {
    "coordinatesV1": "com.sandinh:scala-soap_2.11:1.3.0",
    "coordinatesV2": "com.sandinh:scala-soap_2.11:1.5.0",
    "caller": "|java+method:///com/sandinh/soap/WS$class/call(com.sandinh.soap.WS,java.lang.Object,scala.xml.NamespaceBinding,scala.collection.Seq,com.sandinh.xml.XmlWriter,com.sandinh.xml.XmlReader)|",
    "called": "|java+method:///scala/collection/mutable/StringBuilder/toString()|",
    "v1Body": [
      "|java+method:///scala/concurrent/Future/map(scala.Function1,scala.concurrent.ExecutionContext)|",
      "|java+method:///org/slf4j/Logger/debug(java.lang.String,java.lang.Object%5B%5D)|",
      "|java+method:///scala/Predef$/ArrowAssoc(java.lang.Object)|",
      "|java+constructor:///com/sandinh/soap/WS$$anonfun$call$1/WS$$anonfun$call$1(com.sandinh.soap.WS,com.sandinh.xml.XmlReader)|",
      "|java+method:///play/api/libs/ws/WSRequestHolder/withMethod(java.lang.String)|",
      "|java+method:///play/api/libs/ws/WSRequestHolder/withBody(play.api.libs.ws.WSBody)|",
      "|java+method:///scala/runtime/BoxesRunTime/boxToInteger(int)|",
      "|java+constructor:///scala/collection/mutable/StringBuilder/StringBuilder()|",
      "|java+method:///java/lang/String/getBytes(java.lang.String)|",
      "|java+method:///scala/collection/mutable/StringBuilder/append(java.lang.Object)|",
      "|java+method:///scala/concurrent/ExecutionContext$Implicits$/global()|",
      "|java+method:///com/sandinh/soap/SOAP$/toSoap(java.lang.Object,scala.xml.NamespaceBinding,com.sandinh.xml.XmlWriter)|",
      "|java+method:///java/lang/Object/toString()|",
      "|java+method:///scala/collection/Seq$/canBuildFrom()|",
      "|java+method:///play/api/Play$/current()|",
      "|java+constructor:///play/api/libs/ws/InMemoryBody/InMemoryBody(byte%5B%5D)|",
      "|java+method:///scala/xml/Elem/buildString(boolean)|",
      "|java+method:///play/api/libs/ws/WSRequestHolder/withHeaders(scala.collection.Seq)|",
      "|java+method:///scala/Predef$ArrowAssoc$/$minus$greater$extension(java.lang.Object,java.lang.Object)|",
      "|java+method:///scala/collection/Seq/$colon$plus(java.lang.Object,scala.collection.generic.CanBuildFrom)|",
      "|java+method:///play/api/http/HeaderNames$/CONTENT_LENGTH()|",
      "|java+method:///com/sandinh/soap/WS/logger()|",
      "|java+method:///play/api/libs/ws/WS$/url(java.lang.String,play.api.Application)|",
      "|java+method:///play/api/libs/ws/WSRequestHolder/execute()|",
      "|java+method:///scala/collection/mutable/StringBuilder/toString()|",
      "|java+method:///com/sandinh/soap/WS/url()|"
    ],
    "v2Body": [
      "|java+method:///scala/concurrent/Future/map(scala.Function1,scala.concurrent.ExecutionContext)|",
      "|java+method:///play/api/libs/ws/WSRequest/withBody(play.api.libs.ws.WSBody)|",
      "|java+method:///scala/Predef$/ArrowAssoc(java.lang.Object)|",
      "|java+constructor:///com/sandinh/soap/WS$$anonfun$call$1/WS$$anonfun$call$1(com.sandinh.soap.WS,com.sandinh.xml.XmlReader)|",
      "|java+method:///scala/runtime/BoxesRunTime/boxToInteger(int)|",
      "|java+constructor:///scala/collection/mutable/StringBuilder/StringBuilder()|",
      "|java+method:///java/lang/String/getBytes(java.lang.String)|",
      "|java+method:///scala/collection/mutable/StringBuilder/append(java.lang.Object)|",
      "|java+method:///scala/concurrent/ExecutionContext$Implicits$/global()|",
      "|java+method:///com/sandinh/soap/SOAP$/toSoap(java.lang.Object,scala.xml.NamespaceBinding,com.sandinh.xml.XmlWriter)|",
      "|java+method:///play/api/libs/ws/WSRequest/withMethod(java.lang.String)|",
      "|java+method:///play/api/libs/ws/WS$/url(java.lang.String,play.api.Application)|",
      "|java+method:///java/lang/Object/toString()|",
      "|java+method:///scala/collection/Seq$/canBuildFrom()|",
      "|java+method:///play/api/Play$/current()|",
      "|java+constructor:///play/api/libs/ws/InMemoryBody/InMemoryBody(byte%5B%5D)|",
      "|java+method:///scala/xml/Elem/buildString(boolean)|",
      "|java+method:///org/slf4j/Logger/debug(java.lang.String,java.lang.Object%5B%5D)|",
      "|java+method:///play/api/libs/ws/WSRequest/withHeaders(scala.collection.Seq)|",
      "|java+method:///play/api/libs/ws/WSRequest/execute()|",
      "|java+method:///scala/Predef$ArrowAssoc$/$minus$greater$extension(java.lang.Object,java.lang.Object)|",
      "|java+method:///scala/collection/Seq/$colon$plus(java.lang.Object,scala.collection.generic.CanBuildFrom)|",
      "|java+method:///play/api/http/HeaderNames$/CONTENT_LENGTH()|",
      "|java+method:///com/sandinh/soap/WS/logger()|",
      "|java+method:///scala/collection/mutable/StringBuilder/toString()|",
      "|java+method:///com/sandinh/soap/WS/url()|"
    ],
    "affectedLib": "org.scala-lang:scala-library:2.11.7",
    "change": "UPDATED"
  },
  {
    "coordinatesV1": "com.sandinh:scala-soap_2.11:1.3.0",
    "coordinatesV2": "com.sandinh:scala-soap_2.11:1.5.0",
    "caller": "|java+method:///com/sandinh/soap/WS$class/call(com.sandinh.soap.WS,java.lang.Object,scala.xml.NamespaceBinding,scala.collection.Seq,com.sandinh.xml.XmlWriter,com.sandinh.xml.XmlReader)|",
    "called": "|java+method:///play/api/libs/ws/WS$/url(java.lang.String,play.api.Application)|",
    "v1Body": [
      "|java+method:///scala/concurrent/Future/map(scala.Function1,scala.concurrent.ExecutionContext)|",
      "|java+method:///org/slf4j/Logger/debug(java.lang.String,java.lang.Object%5B%5D)|",
      "|java+method:///scala/Predef$/ArrowAssoc(java.lang.Object)|",
      "|java+constructor:///com/sandinh/soap/WS$$anonfun$call$1/WS$$anonfun$call$1(com.sandinh.soap.WS,com.sandinh.xml.XmlReader)|",
      "|java+method:///play/api/libs/ws/WSRequestHolder/withMethod(java.lang.String)|",
      "|java+method:///play/api/libs/ws/WSRequestHolder/withBody(play.api.libs.ws.WSBody)|",
      "|java+method:///scala/runtime/BoxesRunTime/boxToInteger(int)|",
      "|java+constructor:///scala/collection/mutable/StringBuilder/StringBuilder()|",
      "|java+method:///java/lang/String/getBytes(java.lang.String)|",
      "|java+method:///scala/collection/mutable/StringBuilder/append(java.lang.Object)|",
      "|java+method:///scala/concurrent/ExecutionContext$Implicits$/global()|",
      "|java+method:///com/sandinh/soap/SOAP$/toSoap(java.lang.Object,scala.xml.NamespaceBinding,com.sandinh.xml.XmlWriter)|",
      "|java+method:///java/lang/Object/toString()|",
      "|java+method:///scala/collection/Seq$/canBuildFrom()|",
      "|java+method:///play/api/Play$/current()|",
      "|java+constructor:///play/api/libs/ws/InMemoryBody/InMemoryBody(byte%5B%5D)|",
      "|java+method:///scala/xml/Elem/buildString(boolean)|",
      "|java+method:///play/api/libs/ws/WSRequestHolder/withHeaders(scala.collection.Seq)|",
      "|java+method:///scala/Predef$ArrowAssoc$/$minus$greater$extension(java.lang.Object,java.lang.Object)|",
      "|java+method:///scala/collection/Seq/$colon$plus(java.lang.Object,scala.collection.generic.CanBuildFrom)|",
      "|java+method:///play/api/http/HeaderNames$/CONTENT_LENGTH()|",
      "|java+method:///com/sandinh/soap/WS/logger()|",
      "|java+method:///play/api/libs/ws/WS$/url(java.lang.String,play.api.Application)|",
      "|java+method:///play/api/libs/ws/WSRequestHolder/execute()|",
      "|java+method:///scala/collection/mutable/StringBuilder/toString()|",
      "|java+method:///com/sandinh/soap/WS/url()|"
    ],
    "v2Body": [
      "|java+method:///scala/concurrent/Future/map(scala.Function1,scala.concurrent.ExecutionContext)|",
      "|java+method:///play/api/libs/ws/WSRequest/withBody(play.api.libs.ws.WSBody)|",
      "|java+method:///scala/Predef$/ArrowAssoc(java.lang.Object)|",
      "|java+constructor:///com/sandinh/soap/WS$$anonfun$call$1/WS$$anonfun$call$1(com.sandinh.soap.WS,com.sandinh.xml.XmlReader)|",
      "|java+method:///scala/runtime/BoxesRunTime/boxToInteger(int)|",
      "|java+constructor:///scala/collection/mutable/StringBuilder/StringBuilder()|",
      "|java+method:///java/lang/String/getBytes(java.lang.String)|",
      "|java+method:///scala/collection/mutable/StringBuilder/append(java.lang.Object)|",
      "|java+method:///scala/concurrent/ExecutionContext$Implicits$/global()|",
      "|java+method:///com/sandinh/soap/SOAP$/toSoap(java.lang.Object,scala.xml.NamespaceBinding,com.sandinh.xml.XmlWriter)|",
      "|java+method:///play/api/libs/ws/WSRequest/withMethod(java.lang.String)|",
      "|java+method:///play/api/libs/ws/WS$/url(java.lang.String,play.api.Application)|",
      "|java+method:///java/lang/Object/toString()|",
      "|java+method:///scala/collection/Seq$/canBuildFrom()|",
      "|java+method:///play/api/Play$/current()|",
      "|java+constructor:///play/api/libs/ws/InMemoryBody/InMemoryBody(byte%5B%5D)|",
      "|java+method:///scala/xml/Elem/buildString(boolean)|",
      "|java+method:///org/slf4j/Logger/debug(java.lang.String,java.lang.Object%5B%5D)|",
      "|java+method:///play/api/libs/ws/WSRequest/withHeaders(scala.collection.Seq)|",
      "|java+method:///play/api/libs/ws/WSRequest/execute()|",
      "|java+method:///scala/Predef$ArrowAssoc$/$minus$greater$extension(java.lang.Object,java.lang.Object)|",
      "|java+method:///scala/collection/Seq/$colon$plus(java.lang.Object,scala.collection.generic.CanBuildFrom)|",
      "|java+method:///play/api/http/HeaderNames$/CONTENT_LENGTH()|",
      "|java+method:///com/sandinh/soap/WS/logger()|",
      "|java+method:///scala/collection/mutable/StringBuilder/toString()|",
      "|java+method:///com/sandinh/soap/WS/url()|"
    ],
    "affectedLib": "com.typesafe.play:play-ws_2.11:2.4.6",
    "change": "UPDATED"
  }
]