[
  {
    "coordinatesV1": "com.netflix.ocelli:ocelli-core:0.0.9",
    "coordinatesV2": "com.netflix.ocelli:ocelli-core:0.1.0-rc.1",
    "caller": "|java+method:///netflix/ocelli/util/RxUtil/onSubscribeChooseNext(rx.Observable%5B%5D)|",
    "called": "|java+method:///rx/Observable/create(rx.Observable$OnSubscribe)|",
    "v1Body": [
      "|java+constructor:///netflix/ocelli/util/RxUtil$20/RxUtil$20(rx.Observable%5B%5D)|",
      "|java+method:///rx/Observable/create(rx.Observable$OnSubscribe)|"
    ],
    "v2Body": [
      "|java+constructor:///netflix/ocelli/util/RxUtil$21/RxUtil$21(rx.Observable%5B%5D)|",
      "|java+method:///rx/Observable/create(rx.Observable$OnSubscribe)|"
    ],
    "affectedLib": "io.reactivex:rxjava:1.0.5",
    "change": "UPDATED"
  },
  {
    "coordinatesV1": "com.netflix.ocelli:ocelli-core:0.0.9",
    "coordinatesV2": "com.netflix.ocelli:ocelli-core:0.1.0-rc.1",
    "caller": "|java+method:///netflix/ocelli/util/RxUtil/conditionAnder(java.util.List)|",
    "called": "|java+method:///rx/Observable/combineLatest(java.util.List,rx.functions.FuncN)|",
    "v1Body": [
      "|java+method:///rx/Observable/distinctUntilChanged()|",
      "|java+constructor:///netflix/ocelli/util/RxUtil$21/RxUtil$21()|",
      "|java+constructor:///netflix/ocelli/util/RxUtil$22/RxUtil$22()|",
      "|java+method:///rx/Observable/flatMap(rx.functions.Func1)|",
      "|java+method:///rx/Observable/combineLatest(java.util.List,rx.functions.FuncN)|"
    ],
    "v2Body": [
      "|java+method:///rx/Observable/distinctUntilChanged()|",
      "|java+constructor:///netflix/ocelli/util/RxUtil$22/RxUtil$22()|",
      "|java+constructor:///netflix/ocelli/util/RxUtil$23/RxUtil$23()|",
      "|java+method:///rx/Observable/flatMap(rx.functions.Func1)|",
      "|java+method:///rx/Observable/combineLatest(java.util.List,rx.functions.FuncN)|"
    ],
    "affectedLib": "io.reactivex:rxjava:1.0.5",
    "change": "UPDATED"
  },
  {
    "coordinatesV1": "com.netflix.ocelli:ocelli-core:0.0.9",
    "coordinatesV2": "com.netflix.ocelli:ocelli-core:0.1.0-rc.1",
    "caller": "|java+method:///netflix/ocelli/functions/Connectors$2/call(java.lang.Object)|",
    "called": "|java+method:///rx/Observable/empty()|",
    "v1Body": [
      "|java+method:///netflix/ocelli/functions/Connectors$2/call(java.lang.Object)|",
      "|java+method:///rx/Observable/just(java.lang.Object)|"
    ],
    "v2Body": [
      "|java+method:///rx/Observable/empty()|",
      "|java+method:///netflix/ocelli/functions/Connectors$2/call(java.lang.Object)|"
    ],
    "affectedLib": "io.reactivex:rxjava:1.0.5",
    "change": "UPDATED"
  }
]