[
  {
    "coordinatesV1": "org.mobicents.diameter:jdiameter-impl:1.7.0.99",
    "coordinatesV2": "org.mobicents.diameter:jdiameter-impl:1.7.0.107",
    "caller": "|java+method:///org/jdiameter/client/impl/parser/ElementParser/bytesToAddress(byte%5B%5D)|",
    "called": "|java+constructor:///org/jdiameter/api/AvpDataException/AvpDataException(java.lang.Throwable)|",
    "v1Body": [
      "|java+constructor:///org/jdiameter/api/AvpDataException/AvpDataException(java.lang.Throwable)|",
      "|java+method:///java/net/Inet4Address/getByAddress(byte%5B%5D)|",
      "|java+method:///java/net/Inet6Address/getByAddress(byte%5B%5D)|",
      "|java+method:///java/lang/System/arraycopy(java.lang.Object,int,java.lang.Object,int,int)|"
    ],
    "v2Body": [
      "|java+method:///java/net/InetAddress/getByAddress(byte%5B%5D)|",
      "|java+constructor:///org/jdiameter/api/AvpDataException/AvpDataException(java.lang.Throwable)|",
      "|java+method:///java/lang/System/arraycopy(java.lang.Object,int,java.lang.Object,int,int)|"
    ],
    "affectedLib": "org.mobicents.diameter:jdiameter-api:1.7.0.107",
    "change": "UPDATED"
  }
]