[
  {
    "coordinatesV1": "org.seleniumhq.selenium:selenium-ie-driver:3.8.1",
    "coordinatesV2": "org.seleniumhq.selenium:selenium-ie-driver:3.9.0",
    "caller": "|java+method:///org/openqa/selenium/ie/InternetExplorerOptions/setCapability(java.lang.String,java.lang.Object)|",
    "called": "|java+method:///org/openqa/selenium/MutableCapabilities/setCapability(java.lang.String,java.lang.Object)|",
    "v1Body": [
      "|java+method:///java/util/Map/put(java.lang.Object,java.lang.Object)|",
      "|java+method:///java/util/Set/stream()|",
      "|java+method:///java/lang/StringBuilder/append(java.lang.String)|",
      "|java+method:///org/openqa/selenium/MutableCapabilities/setCapability(java.lang.String,java.lang.Object)|",
      "|java+method:///java/util/stream/Stream/filter(java.util.function.Predicate)|",
      "|java+method:///java/util/Set/contains(java.lang.Object)|",
      "|java+method:///java/util/Map/clear()|",
      "|java+constructor:///java/lang/IllegalArgumentException/IllegalArgumentException(java.lang.String)|",
      "|java+method:///java/util/Map/entrySet()|",
      "|java+method:///java/lang/StringBuilder/toString()|",
      "|java+method:///java/lang/String/equals(java.lang.Object)|",
      "|java+method:///org/openqa/selenium/Capabilities/asMap()|",
      "|java+constructor:///java/lang/StringBuilder/StringBuilder()|",
      "|java+method:///java/util/stream/Stream/forEach(java.util.function.Consumer)|"
    ],
    "v2Body": [
      "|java+method:///java/util/stream/Stream/map(java.util.function.Function)|",
      "|java+method:///java/util/Map/put(java.lang.Object,java.lang.Object)|",
      "|java+method:///java/lang/StringBuilder/append(java.lang.String)|",
      "|java+method:///java/util/List/stream()|",
      "|java+method:///java/util/stream/Collectors/joining(java.lang.CharSequence)|",
      "|java+method:///org/openqa/selenium/MutableCapabilities/setCapability(java.lang.String,java.lang.Object)|",
      "|java+method:///java/util/stream/Stream/filter(java.util.function.Predicate)|",
      "|java+method:///java/util/Set/contains(java.lang.Object)|",
      "|java+method:///java/util/Map/clear()|",
      "|java+constructor:///java/lang/IllegalArgumentException/IllegalArgumentException(java.lang.String)|",
      "|java+method:///java/util/Map/entrySet()|",
      "|java+method:///java/lang/StringBuilder/toString()|",
      "|java+method:///java/util/Set/stream()|",
      "|java+method:///java/util/stream/Stream/collect(java.util.stream.Collector)|",
      "|java+method:///java/lang/String/equals(java.lang.Object)|",
      "|java+method:///org/openqa/selenium/Capabilities/asMap()|",
      "|java+constructor:///java/lang/StringBuilder/StringBuilder()|",
      "|java+method:///java/util/stream/Stream/forEach(java.util.function.Consumer)|"
    ],
    "affectedLib": "org.seleniumhq.selenium:selenium-api:3.9.0",
    "change": "UPDATED"
  },
  {
    "coordinatesV1": "org.seleniumhq.selenium:selenium-ie-driver:3.8.1",
    "coordinatesV2": "org.seleniumhq.selenium:selenium-ie-driver:3.9.0",
    "caller": "|java+method:///org/openqa/selenium/ie/InternetExplorerOptions/addCommandSwitches(java.lang.String%5B%5D)|",
    "called": "|java+method:///com/google/common/collect/Streams/concat(java.util.stream.Stream%5B%5D)|",
    "v1Body": [
      "|java+method:///org/openqa/selenium/ie/InternetExplorerOptions/getCapability(java.lang.String)|",
      "|java+method:///java/util/stream/Stream/collect(java.util.stream.Collector)|",
      "|java+method:///com/google/common/collect/Streams/concat(java.util.stream.Stream%5B%5D)|",
      "|java+method:///java/util/List/stream()|",
      "|java+constructor:///java/util/LinkedList/LinkedList()|",
      "|java+method:///java/lang/Object/getClass()|",
      "|java+method:///java/util/stream/Stream/of(java.lang.Object%5B%5D)|",
      "|java+method:///org/openqa/selenium/ie/InternetExplorerOptions/amend(java.lang.String,java.lang.Object)|",
      "|java+method:///java/util/stream/Stream/map(java.util.function.Function)|",
      "|java+method:///java/util/stream/Stream/filter(java.util.function.Predicate)|",
      "|java+method:///com/google/common/collect/ImmutableList/toImmutableList()|",
      "|java+method:///java/lang/Class/cast(java.lang.Object)|"
    ],
    "v2Body": [
      "|java+method:///java/lang/String/split(java.lang.String)|",
      "|java+method:///org/openqa/selenium/ie/InternetExplorerOptions/getCapability(java.lang.String)|",
      "|java+method:///java/util/stream/Stream/collect(java.util.stream.Collector)|",
      "|java+method:///com/google/common/collect/Streams/concat(java.util.stream.Stream%5B%5D)|",
      "|java+method:///java/util/Arrays/asList(java.lang.Object%5B%5D)|",
      "|java+method:///java/util/List/stream()|",
      "|java+constructor:///java/util/LinkedList/LinkedList()|",
      "|java+method:///java/lang/Object/getClass()|",
      "|java+method:///java/util/stream/Stream/of(java.lang.Object%5B%5D)|",
      "|java+method:///org/openqa/selenium/ie/InternetExplorerOptions/amend(java.lang.String,java.lang.Object)|",
      "|java+method:///java/util/stream/Stream/map(java.util.function.Function)|",
      "|java+method:///java/util/stream/Stream/filter(java.util.function.Predicate)|",
      "|java+method:///com/google/common/collect/ImmutableList/toImmutableList()|",
      "|java+method:///java/lang/Class/cast(java.lang.Object)|"
    ],
    "affectedLib": "com.google.guava:guava:23.6-jre",
    "change": "UPDATED"
  }
]